{"2":[["アジ",1],["イナダ",1],["サヨリ",1]],"3":[["セイゴ（スズキ）",2],["クロダイ",1]],"4":[["アジ",5],["サワラ",3],["メジロ",3]],"5":[["サバ",1],["ショゴ",1],["ツムブリ",1]],"6":[["メッキ",4],["クロダイ",3],["ヤズ",3]],"8":[["スモールマウスバス",9]],"9":[["ブラックバス",1]],"10":[["アオリイカ",8],["アジ",8],["サゴシ",5]],"11":[["アオリイカ",1],["サバ",1]],"12":[["ブラックバス",3]],"13":[["サゴシ",5],["アオリイカ",3],["マゴチ",3]],"14":[["アイナメ",9],["サバ",6],["イナダ",4]],"15":[["ブラックバス",1]],"18":[["アオリイカ",64],["サゴシ",16],["カマス",14]],"19":[["タチウオ",1]],"20":[["ナマズ",1],["ブラックバス",1]],"21":[["ヒラメ",5],["スズキ",3],["マゴチ",3]],"22":[["スズキ",3],["イナダ",1],["キビレ",1]],"23":[["アジ",7],["ワラサ",6],["スズキ",5]],"24":[["スズキ",4],["マイワシ",4],["カタクチイワシ",3]],"26":[["アジ",2]],"27":[["アジ",1]],"28":[["スモールマウスバス",8],["オイカワ",1]],"29":[["ブラックバス",1]],"30":[["サゴシ",2],["サバ",1],["ソゲ",1]],"31":[["スモールマウスバス",2],["ブラックバス",1],["ラージマウスバス",1]],"32":[["キントキダイ",1]],"33":[["サゴシ",10],["アオリイカ",7],["アジ",4]],"34":[["スズキ",7],["クロソイ",4],["アオリイカ",3]],"35":[["タチウオ",4],["サゴシ",2],["イナダ",1]],"36":[["アイナメ",1],["ムツ",1],["ワラサ",1]],"37":[["ブラックバス",6]],"38":[["ブラックバス",31],["ナマズ",3],["スズキ",2]],"39":[["サゴシ",26],["アジ",24],["スズキ",18]],"40":[["タチウオ",2],["アオリイカ",1],["アジ",1]],"41":[["ブラックバス",10]],"42":[["スズキ",1]],"43":[["スズキ",17],["ソゲ",2],["ヒラメ",2]],"44":[["マハゼ",2],["セイゴ（スズキ）",1]],"45":[["アオリイカ",6],["スズキ",5],["ヒラメ",4]],"46":[["カサゴ",3],["タケノコメバル",2],["マゴチ",2]],"47":[["ヒラメ",5],["アジ",3],["サゴシ",2]],"49":[["アオリイカ",3],["アジ",3],["クロダイ",2]],"50":[["イナダ",1],["サゴシ",1]],"51":[["ブラックバス",1],["ラージマウスバス",1]],"52":[["ブラックバス",3]],"55":[["アオリイカ",10],["ヤズ",8],["キジハタ",7]],"56":[["ブラックバス",9],["ラージマウスバス",2],["マハゼ",1]],"57":[["アイナメ",1]],"58":[["アオリイカ",5],["アジ",4],["ワラサ",2]],"59":[["ヒラメ",1]],"61":[["スズキ",5],["サバ",2],["タコ",2]],"62":[["アジ",1]],"63":[["ヒラメ",43],["スズキ",14],["ソゲ",14]],"64":[["サゴシ",8],["アオリイカ",5],["スズキ",4]],"67":[["アイナメ",1],["アナゴ",1],["イトヒキアジ",1]],"68":[["ショゴ",3],["ホウボウ",3],["メッキ",2]],"69":[["スズキ",4],["ヒラメ",2],["マダイ",2]],"70":[["タチウオ",2],["カマス",1],["ソゲ",1]],"72":[["アオリイカ",7],["アジ",4],["カサゴ",2]],"73":[["アジ",14],["アオリイカ",9],["カワハギ",4]],"74":[["アジ",3],["アナゴ",1],["イナダ",1]],"75":[["クロソイ",4],["ワラサ",2],["イナダ",1]],"76":[["アオリイカ",1],["エソ",1],["オオモンハタ",1]],"77":[["マイワシ",10],["アジ",7],["イワシ",6]],"78":[["スズキ",1]],"79":[["イナダ",14],["マアジ",10],["アジ",9]],"80":[["スズキ",5],["ワラサ",1]],"81":[["スズキ",4],["カニ",1],["シタビラメ",1]],"82":[["アオリイカ",3],["アジ",2],["サバ",2]],"83":[["アオリイカ",2],["カサゴ",2],["ブリ",2]],"84":[["キジハタ",3],["アジ",2],["アイゴ",1]],"85":[["イナダ",1],["シロサバフグ",1]],"86":[["コイ",1],["スズキ",1]],"87":[["サゴシ",3],["アジ",2],["スズキ",1]],"88":[["アオリイカ",1]],"89":[["アオリイカ",2],["イナダ",2],["アジ",1]],"90":[["ヒラメ",1]],"92":[["フグ",1]],"93":[["アジ",5],["マアジ",2],["アイゴ",1]],"94":[["マゴチ",9],["アジ",6],["カサゴ",2]],"96":[["スズキ",34],["マゴチ",4],["セイゴ（スズキ）",3]],"97":[["カサゴ",5],["タイ",4],["クロダイ",3]],"98":[["エソ",1]],"99":[["アジ",2],["カサゴ",2],["キジハタ",2]],"100":[["スズキ",76],["サワラ",3],["カサゴ",2]],"103":[["アジ",24],["スズキ",15],["サゴシ",11]],"104":[["アオリイカ",8],["サゴシ",2],["ヤズ",2]],"105":[["サワラ",4],["スズキ",3],["マダイ",3]],"106":[["ミナミギンガメアジ",1],["ヨメヒメジ",1]],"107":[["カタクチイワシ",4],["サッパ",3],["セイゴ（スズキ）",3]],"108":[["スズキ",5],["クロダイ",2],["ヒラスズキ",1]],"109":[["スモールマウスバス",2]],"110":[["アオリイカ",1],["エソ",1],["サケ",1]],"111":[["スズキ",9],["ヒラメ",4],["セイゴ（スズキ）",3]],"112":[["アジ",1],["スズキ",1],["セイゴ（スズキ）",1]],"113":[["スズキ",8]],"114":[["カサゴ",1]],"116":[["タチウオ",2],["カサゴ",1],["サゴシ",1]],"117":[["アオリイカ",19],["サゴシ",7],["アジ",4]],"118":[["メジナ",3],["カサゴ",2],["ウチワザメ",1]],"119":[["アジ",30],["サゴシ",16],["アオリイカ",13]],"121":[["ヒラメ",14],["スズキ",9],["ワカシ",4]],"123":[["アオリイカ",5],["サゴシ",4],["マダイ",4]],"124":[["アジ",1],["サバ",1],["スズキ",1]],"125":[["カサゴ",2],["スズキ",2]],"126":[["マダイ",4],["マゴチ",3],["アジ",2]],"127":[["スズキ",12],["コノシロ",1],["ツバクロエイ",1]],"128":[["ヤズ",4],["アオリイカ",3],["サゴシ",1]],"129":[["アカハタ",3],["オオモンハタ",3],["アオリイカ",2]],"130":[["スモールマウスバス",4],["スズキ",3],["ラージマウスバス",1]],"131":[["イナダ",5],["アオリイカ",3],["サゴシ",2]],"132":[["コノシロ",1],["スズキ",1],["フッコ（スズキ）",1]],"134":[["ボラ",1]],"135":[["カサゴ",4],["アジ",3],["マゴチ",3]],"136":[["アオリイカ",2],["イイダコ",1],["キス",1]],"139":[["アオリイカ",2],["サゴシ",1]],"140":[["イナダ",2],["タチウオ",2],["エソ",1]],"141":[["ナマズ",17],["スズキ",4],["ブラックバス",3]],"142":[["アオリイカ",1],["サゴシ",1]],"143":[["タチウオ",11],["アジ",9],["スズキ",7]],"145":[["アジ",3],["サワラ",2],["ブリ",2]],"146":[["アジ",6],["タチウオ",3],["サバ",2]],"147":[["スズキ",3]],"149":[["サゴシ",4],["アオリイカ",2],["キビレ",1]],"150":[["スズキ",1]],"151":[["マメイカ",6],["クロソイ",2],["サバ",2]],"152":[["ハマチ",5],["アオリイカ",3],["エソ",3]],"153":[["アジ",15],["ヒラメ",8],["クロムツ",7]],"156":[["メッキ",2],["イシダイ",1],["サッパ",1]],"157":[["ヒラメ",5],["スズキ",4],["ソゲ",2]],"158":[["アジ",2],["クロダイ",2],["スズキ",1]],"159":[["キジハタ",2],["アオリイカ",1],["アカエイ",1]],"160":[["マゴチ",17],["スズキ",16],["マアジ",7]],"161":[["アジ",4],["キス",1],["マダコ",1]],"162":[["ブリ",1]],"163":[["マハゼ",3],["ウグイ",2],["マメイカ",2]],"165":[["スズキ",3],["クロダイ",1],["マアジ",1]],"166":[["カサゴ",3],["アジ",2],["キジハタ",2]],"167":[["アオリイカ",2],["イナダ",1],["サゴシ",1]],"168":[["スズキ",9],["キビレ",2],["アカカマス",1]],"169":[["サゴシ",5],["エソ",1],["カサゴ",1]],"170":[["ブラックバス",5]],"171":[["ブラックバス",9],["クロダイ",1],["スズキ",1]],"172":[["スズキ",4],["クロダイ",3],["マハゼ",3]],"173":[["ヒラメ",35],["ソゲ",6],["スズキ",4]],"174":[["アオリイカ",7],["アジ",6],["イナダ",1]],"175":[["カマス",3],["サゴシ",3],["ソゲ",2]],"176":[["ヒラメ",21],["ソゲ",5],["ショゴ",1]],"177":[["スズキ",3],["サゴシ",2],["ヒラメ",1]],"178":[["スズキ",5],["ヒラメ",3],["マゴチ",3]],"179":[["カマス",2],["イシモチ",1],["ソゲ",1]],"180":[["ブラックバス",2],["ラージマウスバス",1]],"182":[["コノシロ",1],["マハゼ",1]],"183":[["スズキ",10],["フッコ（スズキ）",4],["セイゴ（スズキ）",1]],"184":[["ブラックバス",1],["マハゼ",1]],"185":[["アオリイカ",2],["サワラ",1]],"186":[["ヒラメ",3],["マダイ",2],["ワラサ",2]],"187":[["サゴシ",4],["アオリイカ",3],["ソゲ",3]],"188":[["アオリイカ",5],["サゴシ",2],["シイラ",2]],"189":[["アジ",9],["マイワシ",5],["マアジ",4]],"190":[["アオリイカ",2],["モンゴウイカ",1]],"191":[["アジ",9],["ヒラメ",3],["アナゴ",2]],"193":[["スズキ",2],["サゴシ",1],["ソゲ",1]],"194":[["タチウオ",6],["シイラ",3],["ヒラメ",3]],"195":[["サゴシ",3],["アジ",2],["カマス",1]],"196":[["スズキ",1]],"197":[["サゴシ",9],["アジ",2],["カサゴ",1]],"200":[["サゴシ",19],["タチウオ",6],["アジ",4]],"201":[["スズキ",10],["ヒラメ",6],["マゴチ",3]],"202":[["マゴチ",2]],"203":[["スズキ",3],["セイゴ（スズキ）",1],["メッキ",1]],"204":[["マゴチ",48],["タチウオ",35],["ニベ",24]],"205":[["アカササノハベラ",1],["アカハタ",1],["カサゴ",1]],"206":[["アジ",2],["カサゴ",1],["タケノコメバル",1]],"207":[["ニジマス",2],["トラウト",1]],"208":[["ウグイ",2],["スズキ",2],["ブラックバス",1]],"209":[["アオリイカ",1],["アジ",1],["サゴシ",1]],"210":[["ギンガメアジ",7],["オニヒラアジ",3],["イシミーバイ",2]],"212":[["サゴシ",1],["スズキ",1],["ハマチ",1]],"213":[["ブラックバス",6],["スズキ",2],["アオリイカ",1]],"214":[["スズキ",22],["クロダイ",13],["マハゼ",9]],"215":[["ヒラメ",4],["アオリイカ",3],["マゴチ",3]],"216":[["ブラックバス",3],["ナマズ",1],["ブルーギル",1]],"217":[["ブラックバス",5]],"218":[["スズキ",14],["クロダイ",6],["マイワシ",1]],"220":[["アオリイカ",8],["アマダイ",2],["アカムツ",1]],"221":[["ブラックバス",2]],"222":[["スズキ",5],["サゴシ",4],["アジ",1]],"227":[["スズキ",3],["アカオビシマハゼ",1],["キビレ",1]],"228":[["アジ",2],["タチウオ",2],["アカムツ",1]],"230":[["ソゲ",10],["ヒラメ",5],["タチウオ",3]],"231":[["アジ",13],["スズキ",11],["アオリイカ",10]],"232":[["タチウオ",12],["ヒラメ",6],["アオリイカ",4]],"233":[["スズキ",5],["アメリカナマズ",1]],"234":[["ギンガメアジ",4],["オニカサゴ",1],["カスミアジ",1]],"235":[["スズキ",1]],"236":[["サケ",1],["シマソイ",1],["シャコ",1]],"237":[["サゴシ",18],["アオリイカ",4],["コゾクラ",3]],"238":[["ブラックバス",3],["アジ",1],["イタチウオ",1]],"239":[["スズキ",7],["サワラ",6],["ハマチ",4]],"240":[["ニゴイ",1]],"241":[["スズキ",2],["アオリイカ",1],["サゴシ",1]],"242":[["タチウオ",1]],"244":[["ブリ",1]],"245":[["イナダ",2],["タチウオ",2],["アジ",1]],"247":[["アジ",2]],"249":[["アオリイカ",7],["イナダ",4],["カワハギ",3]],"250":[["サゴシ",5],["アジ",2],["アオリイカ",1]],"251":[["ブラックバス",3]],"252":[["ヒラメ",29],["マゴチ",19],["ソゲ",13]],"254":[["ヒラスズキ",4],["サメ",2],["セイゴ（ヒラスズキ）",2]],"255":[["アジ",1],["キビレ",1],["クロホシフエダイ",1]],"256":[["クロダイ",2],["チンチン",1]],"257":[["スズキ",15],["アメリカナマズ",5],["ブラックバス",3]],"258":[["スズキ",13],["セイゴ（タイリクスズキ）",1]],"259":[["セイゴ（ヒラスズキ）",2],["ソゲ",2],["マゴチ",2]],"260":[["スズキ",16],["アジ",10],["カサゴ",4]],"261":[["スズキ",4],["イナダ",1]],"262":[["ブラックバス",3]],"264":[["スモールマウスバス",3],["ブラックバス",2],["ウグイ",1]],"265":[["アジ",3],["アオリイカ",2]],"266":[["マゴチ",2],["コバンアジ",1],["セイゴ（ヒラスズキ）",1]],"267":[["アオリイカ",6],["メジロ",5],["サゴシ",4]],"268":[["アオリイカ",4],["シイラ",4],["イナダ",3]],"269":[["ブラックバス",1]],"270":[["スズキ",8],["コノシロ",4],["カタクチイワシ",3]],"271":[["ブラックバス",1]],"274":[["スズキ",17],["ハクレン",1]],"276":[["アジ",1],["サワラ",1],["ソゲ",1]],"277":[["ラージマウスバス",6],["ブラックバス",3]],"278":[["カマス",3],["キス",2],["ウルメイワシ",1]],"279":[["アオリイカ",2],["サゴシ",2],["メイタ",2]],"280":[["ブラックバス",3],["ラージマウスバス",3],["ブルーギル",2]],"282":[["スズキ",24],["クロダイ",3],["キビレ",1]],"285":[["クサフグ",2],["セイゴ（ヒラスズキ）",1],["ダツ",1]],"286":[["メバル",1]],"287":[["アオリイカ",4],["イナダ",3],["アカハタ",2]],"289":[["ヒラメ",3],["アジ",2],["イナダ",2]],"290":[["アメマス",4]],"291":[["サバ",2],["カワハギ",1],["クサフグ",1]],"294":[["アジ",1],["カサゴ",1],["メジロ",1]],"295":[["ブラックバス",1]],"296":[["カサゴ",1]],"297":[["ブラックバス",2]],"300":[["サバ",3],["サゴシ",1]],"301":[["アジ",5],["カサゴ",4],["サバ",4]],"302":[["タチウオ",5],["イナダ",2],["カサゴ",2]],"303":[["クロダイ",1]],"304":[["トウゴロウイワシ",1],["マダイ",1]],"305":[["ブラックバス",5],["ラージマウスバス",1]],"306":[["ラージマウスバス",8],["ナマズ",2],["スズキ",1]],"308":[["アジ",2],["アカエイ",1],["カタクチイワシ",1]],"310":[["タチウオ",8],["アオリイカ",6],["キジハタ",2]],"311":[["ヒラメ",23],["ソゲ",4],["シタビラメ",2]],"312":[["アイナメ",8],["タケノコメバル",4],["スズキ",3]],"313":[["スズキ",9],["ヒラメ",3],["ソゲ",2]],"315":[["イワナ",1],["ナマズ",1]],"317":[["アオリイカ",20],["アジ",10],["マゴチ",4]],"318":[["アオリイカ",2],["イシダイ",1],["キジハタ",1]],"320":[["キビレ",2],["スズキ",1]],"321":[["アジ",1],["カマス",1]],"322":[["ネリゴ",4],["オオモンハタ",2],["ヤズ",2]],"323":[["メバル",2],["アジ",1],["イナダ",1]],"325":[["アジ",12],["コノシロ",6],["スズキ",3]],"327":[["アジ",6],["オオモンハタ",2],["アオリイカ",1]],"328":[["マゴチ",3],["クロダイ",1],["スズキ",1]],"329":[["アナゴ",14],["タケノコメバル",5],["メバル",5]],"330":[["アイナメ",2]],"331":[["スズキ",3],["サゴシ",2],["アジ",1]],"332":[["エソ",5],["スズキ",2],["タチウオ",2]],"333":[["ハモ",1],["ブリ",1]],"334":[["ブラックバス",45],["ラージマウスバス",3],["ナマズ",2]],"335":[["ナマズ",1]],"336":[["スズキ",9],["クロダイ",1],["コノシロ",1]],"337":[["アジ",8],["ヒラメ",5],["イナダ",4]],"338":[["ヒラメ",6],["フクラギ",6],["アイナメ",3]],"339":[["タチウオ",6],["オオモンハタ",4],["ヒラメ",4]],"340":[["アオリイカ",1]],"341":[["キス",3],["アオリイカ",2],["アジ",2]],"343":[["アオリイカ",1],["アジ",1]],"347":[["ブラックバス",1]],"348":[["スズキ",6],["コノシロ",1]],"350":[["スズキ",5],["ハス",1],["ブラックバス",1]],"351":[["クロダイ",2],["スズキ",1]],"352":[["アジ",11],["タチウオ",4],["カマス",3]],"353":[["ブラックバス",20],["ラージマウスバス",4]],"354":[["タチウオ",4],["エソ",2],["オオモンハタ",2]],"355":[["ブラックバス",19],["ラージマウスバス",8],["ブリ",1]],"356":[["マハゼ",2],["カレイ",1],["マダイ",1]],"357":[["スズキ",25],["セイゴ（スズキ）",2],["クロダイ",1]],"358":[["スズキ",2],["キジハタ",1],["クロダイ",1]],"359":[["アオリイカ",4],["カワハギ",4],["タチウオ",3]],"360":[["アオリイカ",2]],"361":[["ブラックバス",3]],"362":[["アオリイカ",5],["サゴシ",2],["ヤズ",2]],"363":[["アオリイカ",2],["アオハタ",1],["イナダ",1]],"364":[["アオリイカ",2],["キス",1],["ダツ",1]],"365":[["スズキ",4],["フッコ（スズキ）",1]],"366":[["ブラックバス",3]],"367":[["マダイ",2]],"368":[["ニジマス",2]],"370":[["メバル",3],["カレイ",1],["クロソイ",1]],"371":[["アオリイカ",7],["クロメジナ",1],["ネリゴ",1]],"372":[["ワカサギ",4]],"373":[["ブラックバス",12],["アジ",4],["メジロ",3]],"374":[["アジ",4],["タケノコメバル",3],["ブリ",3]],"375":[["ニジマス",3],["アオリイカ",1],["アカカマス",1]],"376":[["ヤズ",6],["サゴシ",4],["サワラ",3]],"377":[["スズキ",18],["クロダイ",6],["タチウオ",3]],"378":[["サンマ",4]],"379":[["スズキ",1],["マゴチ",1]],"381":[["ブラックバス",3],["ブルーギル",1]],"383":[["スズキ",2],["フッコ（スズキ）",1]],"384":[["アオリイカ",2],["アカハタ",1],["イナダ",1]],"389":[["アジ",1],["サゴシ",1],["バリ",1]],"390":[["アジ",1]],"391":[["ソゲ",2],["エソ",1],["ヒラメ",1]],"392":[["タチウオ",2],["アオリイカ",1],["サワラ",1]],"393":[["イナダ",6],["フクラギ",6],["サバ",5]],"394":[["クロサバフグ",1],["スズキ",1],["ネイリ",1]],"395":[["アオリイカ",24],["スズキ",4],["イナダ",2]],"397":[["スズキ",14],["アオリイカ",2],["コイ",1]],"398":[["スズキ",16]],"399":[["アオリイカ",2],["ウツボ",1],["タイ",1]],"400":[["イワシ",1],["メッキ",1]],"401":[["カサゴ",2],["キス",1],["クサフグ",1]],"403":[["スズキ",2],["ヒラメ",2],["アナゴ",1]],"404":[["ヒラメ",7],["マゴチ",5],["アオリイカ",4]],"405":[["ヒラメ",23],["ソゲ",19],["スズキ",6]],"407":[["アオリイカ",1],["クロダイ",1]],"408":[["アジ",3],["クロソイ",2],["シイラ",2]],"411":[["タチウオ",11],["マゴチ",11],["イナダ",9]],"412":[["マゴチ",23],["タチウオ",21],["ソゲ",11]],"413":[["サゴシ",1],["タチウオ",1]],"414":[["ソゲ",12],["ヒラメ",12],["マゴチ",5]],"417":[["スズキ",2],["ヒラメ",2],["サバ",1]],"418":[["スズキ",18],["フッコ（スズキ）",5],["ヒラメ",4]],"419":[["メッキ",3],["クサフグ",2],["サゴシ",2]],"420":[["アジ",5],["カサゴ",4],["イシモチ",2]],"421":[["イシモチ",1],["タチウオ",1],["ヒイラギ",1]],"422":[["マゴチ",3],["カサゴ",2],["アオリイカ",1]],"423":[["マゴチ",2],["クロダイ",1],["シタビラメ",1]],"424":[["アジ",11],["カマス",2],["カレイ",1]],"425":[["スズキ",46],["セイゴ（スズキ）",1]],"426":[["ハマチ",1],["ヒラメ",1]],"433":[["サゴシ",4],["スズキ",4],["ヒラメ",3]],"434":[["ヒラメ",3],["スズキ",1],["ソゲ",1]],"435":[["サゴシ",3],["クロダイ",1],["ハマチ",1]],"439":[["スズキ",10],["アジ",4],["タチウオ",4]],"440":[["ブラックバス",5]],"441":[["マダイ",1],["マダコ",1],["ワラサ",1]],"442":[["サッパ",1]],"443":[["ブラックバス",3]],"444":[["アオリイカ",1],["カマス",1],["サワラ",1]],"445":[["スズキ",10],["ブラックバス",9],["ラージマウスバス",2]],"446":[["アジ",4],["アオリイカ",3],["ウマヅラハギ",1]],"447":[["カサゴ",1]],"448":[["アメマス",1],["クロソイ",1]],"449":[["サワラ",1],["スズキ",1],["マハゼ",1]],"450":[["カンパチ",1]],"454":[["アカハタ",1],["アジ",1],["ネイリ",1]],"455":[["エゾイソアイナメ",1],["エゾメバル",1]],"456":[["サワラ",5],["アイナメ",2],["アジ",2]],"457":[["アオリイカ",1],["アカハタ",1],["モンゴウイカ",1]],"458":[["アイナメ",2],["シロメバル",2],["イナダ",1]],"459":[["ヒラメ",5],["ソゲ",4],["メッキ",2]],"460":[["アオリイカ",3],["カワハギ",1],["キジハタ",1]],"461":[["アジ",2],["セイゴ（ヒラスズキ）",1],["メバル",1]],"463":[["アオリイカ",2],["イナダ",2],["アイゴ",1]],"464":[["シタビラメ",1],["ボラ",1]],"467":[["ラージマウスバス",3]],"468":[["アジ",8],["イナダ",2],["カマス",2]],"470":[["サゴシ",1]],"472":[["クロソイ",3],["アイナメ",2],["イナダ",1]],"474":[["スズキ",9]],"475":[["スズキ",1],["ニジマス",1],["ブラックバス",1]],"477":[["サゴシ",12],["アジ",6],["エソ",5]],"478":[["アイナメ",1],["マハゼ",1]],"481":[["アジ",2]],"484":[["ヤリイカ",3],["アイナメ",1],["イナダ",1]],"485":[["ラージマウスバス",6],["カワハギ",1],["ブラックバス",1]],"486":[["ツバス",1]],"488":[["スズキ",3],["カマス",1],["クロダイ",1]],"489":[["スズキ",32],["クロダイ",2],["フッコ（スズキ）",1]],"492":[["アオリイカ",3],["ハガツオ",3],["カマス",2]],"493":[["アオリイカ",1],["クエ",1],["スマガツオ",1]],"495":[["アジ",6],["イワシ",1],["エソ",1]],"496":[["アオリイカ",3],["エソ",2],["タチウオ",2]],"497":[["イナダ",1],["カサゴ",1],["カワハギ",1]],"498":[["アオリイカ",2],["サゴシ",2],["アジ",1]],"502":[["サゴシ",1]],"503":[["アオリイカ",2],["カンパチ",1],["ヒラマサ",1]],"504":[["スズキ",24],["キビレ",1],["クロダイ",1]],"506":[["ブラックバス",9],["ラージマウスバス",3],["ニゴイ",2]],"508":[["キス",1],["マゴチ",1]],"510":[["ブラックバス",3],["ワカサギ",3],["ラージマウスバス",2]],"514":[["ブラックバス",8],["ブルーギル",1]],"516":[["スズキ",5],["アジ",3],["サゴシ",1]],"517":[["スズキ",2]],"518":[["オオクチユゴイ",1],["サヨリ",1]],"520":[["ウナギ",1],["キジハタ",1],["ハマチ",1]],"521":[["アジ",3],["シマソイ",1],["スズキ",1]],"523":[["アジ",2],["アオリイカ",1],["カサゴ",1]],"524":[["スズキ",4],["ニゴイ",1],["フッコ（スズキ）",1]],"525":[["スズキ",4],["コノシロ",1],["タチウオ",1]],"527":[["タチウオ",1],["チャリコ",1]],"528":[["アオリイカ",4],["アジ",1],["キジハタ",1]],"529":[["クロソイ",1],["スズキ",1]],"530":[["ヒラメ",11],["ソゲ",6],["マゴチ",6]],"531":[["アジ",4],["メバル",2],["ワラサ",2]],"532":[["アジ",1],["サゴシ",1]],"533":[["スモールマウスバス",4],["コイ",1]],"534":[["ブラックバス",7]],"535":[["カサゴ",8],["セイゴ（スズキ）",2],["タケノコメバル",2]],"536":[["ブラックバス",1]],"537":[["エソ",1]],"538":[["アオリイカ",1]],"540":[["アイナメ",1],["フッコ（スズキ）",1]],"541":[["アオリイカ",2],["アカビラ",1],["ショゴ",1]],"544":[["スズキ",1]],"545":[["クロダイ",1]],"547":[["サゴシ",1]],"549":[["スズキ",5]],"550":[["カマス",4],["アオリイカ",3],["アカハタ",3]],"552":[["アナゴ",1],["サヨリ",1]],"553":[["スズキ",4],["ウナギ",1],["マゴチ",1]],"555":[["サゴシ",2],["アジ",1],["マアジ",1]],"556":[["イナダ",1],["クロダイ",1]],"559":[["サゴシ",5],["ソゲ",3],["ハマチ",3]],"560":[["マアジ",1],["マダイ",1],["メジナ",1]],"561":[["ヒラメ",7],["ソゲ",3],["ボラ",2]],"562":[["スズキ",4],["ボラ",4],["アジ",1]],"564":[["ダントウボウ",1],["ブラックバス",1],["ヘラブナ",1]],"566":[["アオリイカ",1],["アジ",1],["コウイカ",1]],"567":[["スズキ",4],["タチウオ",1],["ブラックバス",1]],"568":[["ブラックバス",3]],"569":[["アジ",1],["サゴシ",1]],"571":[["アジ",1],["フッコ（ヒラスズキ）",1]],"572":[["マゴチ",4],["ソゲ",2],["ヒラメ",2]],"573":[["アメマス",2],["クロソイ",1],["サケ",1]],"574":[["エソ",1],["ニゴイ",1],["マゴチ",1]],"577":[["サヨリ",2],["クロダイ",1]],"578":[["ソゲ",1]],"580":[["スズキ",16],["マゴチ",2],["クロダイ",1]],"581":[["カマス",2],["スズキ",2],["セイゴ（ヒラスズキ）",2]],"582":[["ブラックバス",1],["ラージマウスバス",1]],"584":[["スズキ",3],["ヒラメ",1]],"585":[["ブラックバス",1]],"587":[["セイゴ（ヒラスズキ）",2]],"590":[["アオリイカ",1],["アジ",1],["イナダ",1]],"596":[["アオリイカ",1],["キジハタ",1],["サゴシ",1]],"597":[["ワカシ",1]],"598":[["スモールマウスバス",2],["スズキ",1],["マブナ",1]],"601":[["アジ",1]],"602":[["アジ",1],["スズキ",1]],"604":[["カサゴ",4],["タコ",4],["マアナゴ",3]],"606":[["イワシ",1],["サバ",1],["マハゼ",1]],"607":[["サワラ",4],["アオリイカ",2],["アジ",2]],"608":[["アジ",6],["タチウオ",5],["アオリイカ",3]],"609":[["サゴシ",2],["ハマチ",2],["スズキ",1]],"610":[["ワラサ",2],["スズキ",1]],"611":[["ウマヅラハギ",1],["ソイ",1],["タコ",1]],"612":[["スズキ",2]],"615":[["スモールマウスバス",5],["ブラックバス",4],["ヘラブナ",1]],"617":[["オオモンハタ",2],["カサゴ",2],["アイゴ",1]],"618":[["スズキ",1]],"622":[["タチウオ",2],["アオリイカ",1],["シロアマダイ",1]],"623":[["サゴシ",5],["アジ",3],["ヒラメ",2]],"626":[["スズキ",5],["サワラ",1],["ソゲ",1]],"628":[["アジ",3],["タコ",2],["アオヤガラ",1]],"629":[["スズキ",1]],"630":[["スズキ",1],["ニゴイ",1],["ハマチ",1]],"631":[["アジ",1],["タチウオ",1]],"633":[["マゴチ",8],["ヒラメ",3],["タチウオ",2]],"635":[["スズキ",3],["タケノコメバル",1],["ハマチ",1]],"636":[["サゴシ",6],["キジハタ",2],["アジ",1]],"637":[["アオリイカ",2],["ブリ",2],["シロアマダイ",1]],"638":[["キス",3],["ゴンズイ",3],["メジナ",2]],"639":[["アオリイカ",1],["アジ",1],["オオモンハタ",1]],"641":[["アジ",2],["アナゴ",1],["ボラ",1]],"642":[["スズキ",1],["ブラックバス",1]],"645":[["アジ",1],["サッパ",1]],"646":[["アイナメ",6],["スズキ",4],["メバル",2]],"648":[["コイ",1],["ブラックバス",1]],"649":[["スズキ",8],["サゴシ",1],["ブラックバス",1]],"652":[["ソゲ",2],["スズキ",1]],"653":[["スズキ",1],["マゴチ",1]],"654":[["タチウオ",2],["アオリイカ",1],["アジ",1]],"655":[["アジ",7],["アオリイカ",3],["スズキ",2]],"657":[["ブラックバス",5],["ラージマウスバス",2]],"660":[["アオリイカ",11],["ヒラマサ",1],["ブリ",1]],"661":[["カサゴ",4],["アジ",2],["スズキ",2]],"664":[["ヒラメ",1],["ブラックバス",1]],"665":[["アオリイカ",5],["アジ",2],["メジロ",1]],"670":[["スズキ",1],["メバル",1]],"671":[["アオリイカ",1],["コウイカ",1],["サゴシ",1]],"672":[["ブラックバス",1]],"675":[["スズキ",7],["キビレ",1]],"676":[["ブラックバス",1]],"677":[["スズキ",2],["ヒラメ",2],["ソゲ",1]],"678":[["ブラックバス",1]],"679":[["サゴシ",1]],"681":[["エソ",1],["サゴシ",1],["サバ",1]],"682":[["アジ",4],["カタクチイワシ",1],["サバ",1]],"685":[["ニジマス",3]],"686":[["ブラックバス",1],["ラージマウスバス",1]],"688":[["アジ",1],["サゴシ",1]],"689":[["アジ",1]],"690":[["セイゴ（スズキ）",1],["メッキ",1]],"691":[["アジ",1],["オニオコゼ",1],["サゴシ",1]],"695":[["スズキ",1]],"696":[["アオリイカ",2],["イラブチャー",1],["タコ",1]],"697":[["マゴチ",5],["カサゴ",3],["キジハタ",1]],"698":[["アオリイカ",1]],"699":[["クロダイ",2],["サゴシ",1],["ハマチ",1]],"706":[["サゴシ",1],["ヤズ",1]],"707":[["ハマチ",2],["エソ",1],["サワラ",1]],"708":[["スズキ",2],["セイゴ（スズキ）",1]],"709":[["サゴシ",1],["シロサバフグ",1],["ハナアナゴ",1]],"710":[["アイナメ",2],["クロソイ",2],["サケ",2]],"711":[["ワカサギ",1]],"712":[["スズキ",1]],"713":[["キビレ",2],["チャイロマルハタ",2],["メッキ",1]],"714":[["イナダ",4],["スズキ",4],["ソゲ",3]],"717":[["スズキ",9],["クロダイ",2],["キビレ",1]],"719":[["ブラックバス",1],["マナマズ",1]],"720":[["ブラックバス",1]],"721":[["アオリイカ",1],["アジ",1],["タチウオ",1]],"722":[["ブラックバス",7],["ワカサギ",1]],"724":[["スズキ",3],["タチウオ",3],["アジ",2]],"726":[["ブラックバス",3],["ラージマウスバス",1]],"727":[["ダツ",3],["カサゴ",1],["サバ",1]],"728":[["アイナメ",5],["メバル",3],["タケノコメバル",2]],"731":[["アオリイカ",3],["ヒラマサ",3],["キジハタ",1]],"732":[["スズキ",6],["ヒラメ",3],["マゴチ",2]],"733":[["ブラックバス",1]],"735":[["エソ",8],["サゴシ",2],["サワラ",2]],"737":[["タチウオ",3],["ウルメイワシ",1]],"738":[["スズキ",3]],"740":[["スズキ",1],["マゴチ",1]],"742":[["タチウオ",1]],"743":[["アメマス",1]],"744":[["コイ",1],["ブルーギル",1]],"746":[["スズキ",1],["ハマチ",1]],"748":[["アジ",2],["エソ",2],["サゴシ",1]],"749":[["アオリイカ",8],["アオハタ",2],["アジ",2]],"750":[["イネゴチ",1]],"751":[["ブラックバス",2]],"752":[["アジ",1],["マダイ",1]],"753":[["スズキ",6],["キビレ",1],["クロダイ",1]],"756":[["アイナメ",4],["アメマス",1],["サケ",1]],"757":[["アジ",6],["アオリイカ",2],["ハマチ",2]],"758":[["ソゲ",6],["ヒラメ",5],["スズキ",3]],"759":[["スズキ",28],["アジ",10],["タチウオ",4]],"762":[["マハゼ",1]],"764":[["アイナメ",2],["アナゴ",1],["サバ",1]],"765":[["スズキ",1]],"766":[["セイゴ（ヒラスズキ）",2],["クロダイ",1],["セイゴ（スズキ）",1]],"769":[["サゴシ",2],["キス",1]],"770":[["アジ",2],["カサゴ",1]],"773":[["ブラックバス",4]],"776":[["アオリイカ",2],["エソ",2],["サゴシ",2]],"777":[["ヒラメ",15],["ソゲ",13],["マゴチ",7]],"779":[["ヒラスズキ",1]],"783":[["スズキ",1],["タチウオ",1]],"785":[["オニカマス",1]],"787":[["マハゼ",1]],"789":[["コウイカ",1]],"790":[["ブラックバス",1]],"791":[["キス",1],["ソゲ",1]],"792":[["スズキ",13],["マゴチ",1]],"793":[["アオリイカ",3],["ケンサキイカ",2],["エソ",1]],"795":[["スモールマウスバス",1]],"799":[["ボラ",1]],"800":[["オニオコゼ",1],["ソゲ",1],["タチウオ",1]],"801":[["スズキ",3],["マハゼ",1]],"803":[["アナゴ",1],["エソ",1]],"804":[["アカエソ",2],["ショゴ",2],["アカハタ",1]],"805":[["アオリイカ",1],["サゴシ",1],["スマガツオ",1]],"807":[["ソゲ",5],["ヒラメ",4],["アカエイ",2]],"809":[["ブラックバス",1]],"810":[["ヒラメ",6],["マゴチ",5],["キス",3]],"811":[["アオリイカ",1],["オオモンハタ",1],["フエフキダイ",1]],"812":[["スズキ",3],["メジロ",2],["シロメバル",1]],"814":[["スズキ",5],["ハクレン",1],["ラージマウスバス",1]],"816":[["ブラックバス",1]],"817":[["スモールマウスバス",1]],"818":[["サゴシ",1],["スズキ",1],["ソイ",1]],"821":[["キビレ",1],["マゴチ",1]],"822":[["サゴシ",2]],"823":[["ショゴ",1]],"824":[["アジ",8],["マアジ",2],["イシモチ",1]],"826":[["ハマチ",2],["ヤズ",2],["キビレ",1]],"828":[["ブラックバス",2]],"830":[["スズキ",15],["クロダイ",2],["コトヒキ",1]],"831":[["サゴシ",2],["オオニベ",1],["カンパチ",1]],"832":[["エソ",2],["サバ",2],["アジ",1]],"833":[["ブラックバス",1]],"835":[["イナダ",1]],"837":[["オオモンハタ",1],["サゴシ",1],["ツバス",1]],"838":[["アジ",1]],"839":[["ソウダガツオ",1]],"840":[["アオリイカ",1],["カマス",1]],"841":[["カサゴ",1],["ハマチ",1]],"843":[["ブラックバス",2]],"844":[["アジ",2]],"845":[["タチウオ",4],["アオリイカ",1]],"846":[["スズキ",9],["ウナギ",1],["クロダイ",1]],"847":[["タチウオ",2],["アオリイカ",1]],"853":[["スズキ",1]],"854":[["アオリイカ",1],["アジ",1],["タケノコメバル",1]],"855":[["アカカマス",1],["カマス",1],["タチウオ",1]],"861":[["アオリイカ",1],["カマス",1],["シマアジ",1]],"862":[["ヒラメ",1]],"863":[["アオリイカ",2],["スズキ",1],["ハマチ",1]],"865":[["アジ",1],["キビレ",1],["サゴシ",1]],"866":[["ヒラメ",2],["ソゲ",1],["ニベ",1]],"868":[["エソ",1],["サゴシ",1],["サバ",1]],"869":[["クロソイ",1],["マダコ",1]],"872":[["ニジマス",2],["ブラックバス",1]],"873":[["スズキ",6]],"874":[["エソ",1],["クロホシマンジュウダイ",1],["サバ",1]],"876":[["アオリイカ",1],["アカササノハベラ",1]],"877":[["ブラックバス",1],["ラージマウスバス",1]],"879":[["アオリイカ",7],["ブリ",2],["アジ",1]],"881":[["ブラックバス",4]],"884":[["スズキ",2]],"885":[["ヒラメ",2],["アオリイカ",1],["アカハタ",1]],"886":[["ヤズ",2],["タコ",1]],"887":[["アジ",1],["マダイ",1]],"890":[["コモンフグ",1],["タイワンガザミ",1],["タケノコメバル",1]],"892":[["スズキ",1]],"893":[["スモールマウスバス",2],["コイ",1],["タモロコ",1]],"894":[["キジハタ",1],["サゴシ",1]],"897":[["スズキ",1],["ダツ",1]],"898":[["アジ",1],["スズキ",1],["マゴチ",1]],"899":[["スズキ",5],["アオリイカ",1],["アジ",1]],"902":[["アオリイカ",6],["コブダイ",2],["タチウオ",1]],"904":[["アオリイカ",1],["オオニベ",1],["キス",1]],"905":[["サゴシ",2],["ヒラメ",1],["マゴチ",1]],"907":[["アジ",1],["イナダ",1],["マゴチ",1]],"909":[["タチウオ",3],["カサゴ",2],["アカカマス",1]],"910":[["アジ",1],["カマス",1],["キジハタ",1]],"911":[["スズキ",3],["マゴチ",2]],"912":[["アカハタ",1],["カサゴ",1],["クエ",1]],"914":[["アオリイカ",5],["アジ",2],["メジナ",2]],"915":[["タチウオ",3],["アオリイカ",2],["カサゴ",2]],"916":[["アカカマス",1],["サゴシ",1],["タコ",1]],"917":[["クロダイ",2],["マゴチ",2],["ヒラメ",1]],"918":[["セイゴ（ヒラスズキ）",1]],"919":[["エソ",1],["キビレ",1]],"920":[["ブラックバス",3],["スズキ",1]],"925":[["スズキ",3],["アオリイカ",2],["アジ",2]],"926":[["シタビラメ",2],["カマス",1],["ソゲ",1]],"927":[["アオリイカ",1]],"929":[["シロサバフグ",1],["ハタ",1]],"933":[["ブラックバス",3]],"938":[["アオリイカ",5],["アカハタ",2],["カサゴ",2]],"939":[["スズキ",3],["シタビラメ",1]],"941":[["エソ",1],["カサゴ",1]],"942":[["ブラックバス",2]],"943":[["アオリイカ",1],["キス",1],["コウイカ",1]],"947":[["スズキ",2],["ダツ",1]],"948":[["エソ",1]],"949":[["アラ",2],["ヒラメ",1],["マダイ",1]],"950":[["スズキ",17],["タチウオ",2],["コノシロ",1]],"952":[["アオリイカ",4]],"953":[["ウナギ",1],["コイ",1]],"955":[["スズキ",1],["マハゼ",1]],"956":[["サゴシ",6],["エソ",2],["アジ",1]],"959":[["アイナメ",1],["サバ",1],["マゾイ",1]],"960":[["アカササノハベラ",1],["イラ",1],["オオモンハタ",1]],"964":[["メッキ",1]],"965":[["サバ",1]],"966":[["アオリイカ",1]],"967":[["セイゴ（スズキ）",2],["スズキ",1]],"968":[["アオリイカ",1],["スズキ",1]],"969":[["ギンガメアジ",2],["アジ",1],["サバ",1]],"973":[["アカハタ",1],["イシガキフグ",1],["シイラ",1]],"974":[["アイナメ",2],["ワラサ",2]],"975":[["カマス",2],["オオモンハタ",1],["モンゴウイカ",1]],"977":[["スズキ",2],["アジ",1],["カレイ",1]],"979":[["タチウオ",7],["カマス",3],["サゴシ",3]],"982":[["アオリイカ",2],["アカハタ",1],["イトヨリダイ",1]],"983":[["アオリイカ",8],["アカハタ",1],["アマダイ",1]],"984":[["ホウボウ",2],["アカハタ",1],["イナダ",1]],"985":[["ブラックバス",5],["ナマズ",1]],"987":[["メバル",1]],"990":[["マゴチ",1]],"992":[["エソ",1],["サバ",1],["ツバス",1]],"993":[["ブラックバス",3],["ナマズ",2]],"994":[["ヒラメ",3],["スズキ",2],["イナダ",1]],"996":[["クロソイ",1],["コマイ",1]],"997":[["タチウオ",7],["アジ",2],["サゴシ",2]],"999":[["ニジマス",1]],"1002":[["アオリイカ",6],["キジハタ",1]],"1004":[["マアジ",6],["アジ",2],["コモンフグ",2]],"1006":[["アジ",3],["アオリイカ",2],["カミナリイカ",1]],"1008":[["マハゼ",1]],"1009":[["サゴシ",1],["サワラ",1],["ハマチ",1]],"1010":[["ラージマウスバス",1]],"1013":[["スズキ",1]],"1019":[["オイカワ",2],["コイ",1]],"1023":[["スズキ",1]],"1024":[["アジ",1]],"1026":[["スズキ",3],["セイゴ（スズキ）",3],["カマス",1]],"1030":[["ヒイラギ",1],["フクラギ",1],["マハゼ",1]],"1032":[["サワラ",3],["アオリイカ",1],["スズキ",1]],"1033":[["アジ",4],["タチウオ",2],["ウツボ",1]],"1034":[["ウマヅラハギ",1],["サバ",1],["ヒラメ",1]],"1035":[["ナンヨウカイワリ",1],["ブリ",1]],"1036":[["サゴシ",3],["カマス",2],["アカカマス",1]],"1037":[["ブラックバス",1]],"1041":[["タチウオ",1]],"1042":[["アオリイカ",2],["マングローブジャック",1]],"1043":[["アオリイカ",1],["イソマグロ",1],["シブダイ",1]],"1045":[["アオリイカ",2]],"1046":[["アオリイカ",1],["アカハタ",1],["イットウダイ",1]],"1047":[["ラージマウスバス",1]],"1048":[["アジ",1]],"1049":[["アオリイカ",5],["ヒラスズキ",1]],"1050":[["タチウオ",3],["サゴシ",1],["ダツ",1]],"1051":[["ヒラメ",3],["メバル",2],["カニ",1]],"1053":[["スズキ",5],["サッパ",1]],"1054":[["スズキ",1]],"1056":[["アイナメ",3],["イナダ",1],["エゾメバル",1]],"1057":[["アジ",3],["カタクチイワシ",1]],"1058":[["クロソイ",1],["ヒラメ",1],["マゴチ",1]],"1059":[["サゴシ",7],["アジ",1],["サバ",1]],"1060":[["サゴシ",14],["エソ",2],["マゴチ",2]],"1061":[["イカ",1]],"1063":[["マアジ",9],["アジ",8],["クロソイ",2]],"1064":[["アオリイカ",7],["アジ",4],["アナゴ",1]],"1065":[["ニジマス",4]],"1066":[["スズキ",1]],"1067":[["タチウオ",6],["ニベ",3],["ダツ",2]],"1068":[["アオリイカ",1],["アジ",1],["ヒラメ",1]],"1069":[["アオリイカ",1],["クロダイ",1],["メイタ",1]],"1074":[["スズキ",1]],"1082":[["サゴシ",2],["サバ",2],["アジ",1]],"1085":[["スズキ",1],["ツバクロエイ",1]],"1089":[["ヒラメ",3],["タチウオ",2],["マゴチ",2]],"1092":[["メバル",1]],"1093":[["アナハゼ",2],["サバ",2],["アイナメ",1]],"1094":[["アジ",2]],"1096":[["クロダイ",6],["スズキ",2],["マゴチ",1]],"1097":[["タチウオ",1]],"1100":[["スズキ",1],["スモールマウスバス",1]],"1103":[["オニオコゼ",1],["スズキ",1]],"1104":[["スズキ",7],["ブラックバス",1]],"1107":[["マハゼ",1]],"1110":[["アオリイカ",11],["アジ",2],["コウイカ",1]],"1112":[["スズキ",1]],"1114":[["ウグイ",1]],"1115":[["アカエイ",1],["アジ",1],["クロダイ",1]],"1116":[["アオリイカ",2],["サヨリ",2]],"1117":[["ヤズ",3],["カレイ",1],["クロダイ",1]],"1120":[["スズキ",1]],"1121":[["アジ",1],["クロダイ",1],["タチウオ",1]],"1123":[["クロダイ",1]],"1124":[["アオリイカ",1],["クロムツ",1]],"1125":[["スズキ",2],["カサゴ",1],["コゾクラ",1]],"1126":[["アオリイカ",1],["シロダイ",1],["スジアラ",1]],"1128":[["ヒラメ",2],["アジ",1],["イナダ",1]],"1129":[["スズキ",7],["サワラ",1],["セイゴ（スズキ）",1]],"1134":[["アオリイカ",4],["ヤズ",3],["タコ",1]],"1135":[["カマス",1],["チャリコ",1],["ムロアジ",1]],"1137":[["ラージマウスバス",1]],"1139":[["ラージマウスバス",1]],"1140":[["ラージマウスバス",2]],"1142":[["クロダイ",1],["フグ",1],["マゴチ",1]],"1143":[["アオリイカ",2],["アカメバル",1],["アジ",1]],"1148":[["スズキ",2],["キビレ",1],["ヒラメ",1]],"1152":[["スズキ",3]],"1155":[["アオリイカ",7],["アジ",5],["タチウオ",3]],"1157":[["アオリイカ",4],["ヤズ",3],["アジ",1]],"1158":[["ブラックバス",3]],"1161":[["スズキ",2]],"1163":[["ブラックバス",8]],"1164":[["シタビラメ",1],["ヒラメ",1],["メジナ",1]],"1165":[["アイナメ",2],["アジ",1],["スズキ",1]],"1167":[["アオリイカ",1],["アジ",1],["コノシロ",1]],"1168":[["サゴシ",4],["ハマチ",1]],"1175":[["アオリイカ",1],["アカカマス",1],["アミメウツボ",1]],"1176":[["キジハタ",1]],"1177":[["アオリイカ",1]],"1179":[["スズキ",2],["ボラ",1]],"1180":[["アオリイカ",1]],"1181":[["スズキ",1],["セイゴ（タイリクスズキ）",1],["マゴチ",1]],"1182":[["スズキ",4],["マハゼ",1]],"1184":[["タチウオ",4],["イケカツオ",1],["チャイロマルハタ",1]],"1185":[["アジ",1]],"1187":[["オオモンハタ",5],["アカハタ",1],["ウミスズメ",1]],"1188":[["サゴシ",1]],"1189":[["ブラックバス",10]],"1192":[["カサゴ",1],["サバ",1],["メジロ",1]],"1193":[["ハマチ",2],["サゴシ",1]],"1194":[["タチウオ",4],["マダイ",4],["アオリイカ",1]],"1195":[["ウグイ",1],["コイ",1],["スズキ",1]],"1197":[["クロダイ",1],["スズキ",1]],"1199":[["アイナメ",1],["アジ",1],["クロソイ",1]],"1203":[["アオリイカ",1],["オオモンハタ",1],["シマアジ",1]],"1205":[["アジ",1],["スズキ",1]],"1206":[["アオリイカ",3],["オオモンハタ",2],["アカハタ",1]],"1207":[["イワナ",1]],"1210":[["ヒラスズキ",1],["フエフキダイ",1]],"1211":[["マダイ",1],["メバル",1]],"1212":[["アジ",3]],"1214":[["イナダ",1],["ショゴ",1],["メッキ",1]],"1215":[["ブラックバス",2],["ラージマウスバス",1]],"1217":[["ブラックバス",1]],"1218":[["ブラックバス",3]],"1220":[["スズキ",1]],"1222":[["イナダ",1],["カサゴ",1],["ヒラマサ",1]],"1225":[["マハゼ",1]],"1230":[["スズキ",5],["ライギョ",1]],"1231":[["スズキ",1],["ツバクロエイ",1]],"1232":[["サケ",1],["スズキ",1],["マゴチ",1]],"1233":[["ソゲ",2],["ヒラメ",2],["イワシ",1]],"1236":[["マゴチ",5],["ワラサ",2],["イナダ",1]],"1239":[["アオリイカ",1]],"1240":[["ショゴ",2],["マゴチ",1],["マハゼ",1]],"1241":[["ブラックバス",14],["ブルーギル",1]],"1243":[["サゴシ",2],["アジ",1],["クロダイ",1]],"1244":[["スズキ",4],["クロダイ",1],["フッコ（スズキ）",1]],"1247":[["サゴシ",17],["サワラ",10],["ハマチ",6]],"1250":[["アオリイカ",3],["カサゴ",3],["カワハギ",2]],"1252":[["ニジマス",1]],"1255":[["ヒラ",1],["メジロ",1]],"1258":[["タコ",1]],"1260":[["ブラックバス",2]],"1262":[["キジハタ",1]],"1267":[["オオモンハタ",1]],"1270":[["スズキ",7],["フッコ（スズキ）",1]],"1274":[["サゴシ",1]],"1275":[["アオリイカ",7],["オオモンハタ",5],["マゴチ",2]],"1276":[["アジ",2]],"1277":[["サゴシ",1]],"1278":[["ソゲ",6],["ヒラメ",4],["マゴチ",4]],"1280":[["アオリイカ",2],["カンパチ",1],["ブリ",1]],"1281":[["ヒラメ",2],["イナダ",1],["ヘダイ",1]],"1284":[["ブラックバス",1]],"1286":[["エソ",2],["サゴシ",2],["メジロ",2]],"1288":[["ブラックバス",5],["ラージマウスバス",1]],"1290":[["ハマチ",1]],"1292":[["アオリイカ",3]],"1293":[["ヒラメ",3],["アイナメ",1],["スルメイカ",1]],"1295":[["ヒラメ",7],["ソゲ",6],["マゴチ",4]],"1296":[["ブラックバス",1]],"1300":[["ブラックバス",1]],"1303":[["ウルメイワシ",1],["カワハギ",1],["キジハタ",1]],"1306":[["サゴシ",1],["ヤズ",1]],"1309":[["ムラソイ",1]],"1310":[["サバ",1],["マハゼ",1],["ヤリイカ",1]],"1311":[["アオリイカ",1],["ハモ",1]],"1312":[["メジナ",1]],"1319":[["ブラックバス",2]],"1321":[["アジ",1],["ゴンズイ",1],["セイゴ（ヒラスズキ）",1]],"1325":[["アジ",2],["アオリイカ",1],["キジハタ",1]],"1326":[["アオリイカ",1]],"1327":[["アジ",1]],"1328":[["ヒラマサ",1]],"1332":[["ソゲ",3],["ヒラメ",2],["フグ",2]],"1335":[["アオリイカ",1],["アジ",1],["タイワンガザミ",1]],"1336":[["クロソイ",1],["ソゲ",1],["マゴチ",1]],"1339":[["アオリイカ",2],["コウイカ",1],["サバ",1]],"1341":[["ハマチ",2],["サゴシ",1]],"1344":[["ブラックバス",2]],"1349":[["ブラックバス",1],["ブルーギル",1]],"1355":[["サゴシ",2],["サワラ",1],["ブリ",1]],"1356":[["アジ",1],["カサゴ",1],["ヒラマサ",1]],"1358":[["ブラックバス",1]],"1359":[["アジ",1],["クロダイ",1],["タチウオ",1]],"1361":[["ヒラメ",2],["マゴチ",1]],"1362":[["アオリイカ",3]],"1364":[["アオリイカ",1],["キジハタ",1],["サゴシ",1]],"1365":[["アジ",1]],"1366":[["スズキ",3],["イナダ",1],["サバ",1]],"1368":[["サゴシ",2],["ヒラメ",2],["アジ",1]],"1371":[["ニジマス",1]],"1372":[["アオリイカ",1],["ゴンズイ",1]],"1374":[["ギンガメアジ",1]],"1376":[["ヒラメ",2],["スズキ",1],["ヒラスズキ",1]],"1377":[["ブリ",1]],"1381":[["イシミーバイ",1]],"1382":[["サゴシ",3],["マゴチ",2],["キス",1]],"1383":[["サゴシ",1],["メバル",1]],"1385":[["アイナメ",3],["アジ",2],["タケノコメバル",2]],"1386":[["マゴチ",2]],"1387":[["アオリイカ",2],["アカハタ",1],["クロアナゴ",1]],"1390":[["クロダイ",1]],"1394":[["アジ",2],["カサゴ",1],["サバ",1]],"1395":[["ブラックバス",2]],"1397":[["ブラックバス",16],["アメリカナマズ",1],["ラージマウスバス",1]],"1398":[["マゴチ",2],["ヒラメ",1]],"1399":[["キス",1],["ヒラメ",1]],"1400":[["アオリイカ",1]],"1403":[["アジ",1],["タケノコメバル",1]],"1405":[["キビレ",1]],"1409":[["マダイ",1]],"1411":[["スズキ",3],["ブラックバス",1]],"1416":[["アオリイカ",1],["カマス",1]],"1417":[["タチウオ",2],["アジ",1],["カサゴ",1]],"1418":[["サンバソウ",1],["シマアジ",1],["スズキ",1]],"1421":[["カワハギ",1]],"1430":[["タチウオ",3]],"1432":[["アジ",1]],"1433":[["アオリイカ",3]],"1434":[["カサゴ",1],["スズキ",1],["メッキ",1]],"1436":[["サワラ",1],["メジロ",1]],"1439":[["ワラサ",2],["ソゲ",1],["ヒラメ",1]],"1440":[["スズキ",2]],"1441":[["スズキ",3]],"1443":[["カサゴ",1]],"1444":[["ブリ",2],["メジナ",1]],"1445":[["マアジ",2],["キビレ",1],["サッパ",1]],"1448":[["クエ",1],["シイラ",1]],"1451":[["イシガキダイ",1],["サワラ",1]],"1453":[["サゴシ",7],["アジ",6],["アオリイカ",3]],"1455":[["ハマチ",4],["カサゴ",2],["キジハタ",2]],"1458":[["アオリイカ",3],["ワラサ",2],["オオモンハタ",1]],"1459":[["サゴシ",1],["ヒラメ",1]],"1462":[["アジ",1]],"1463":[["ヒラマサ",4],["シイラ",1]],"1464":[["スズキ",2],["カマス",1],["クロダイ",1]],"1467":[["アジ",7],["サバ",1]],"1468":[["ブラックバス",4],["ナマズ",1]],"1469":[["ニジマス",1]],"1473":[["アナハゼ",1]],"1474":[["マゴチ",2],["スズキ",1]],"1475":[["タチウオ",2]],"1476":[["アオリイカ",1]],"1477":[["サバ",1]],"1479":[["アジ",2],["カサゴ",1],["ニシキベラ",1]],"1480":[["サゴシ",1],["メジロ",1]],"1481":[["アオリイカ",5],["アカハタ",2],["カサゴ",2]],"1482":[["ソゲ",4],["スズキ",2],["ヒラメ",2]],"1483":[["サゴシ",4],["スズキ",3],["アジ",1]],"1487":[["カサゴ",1]],"1488":[["アオリイカ",1],["アカカマス",1],["カサゴ",1]],"1490":[["アオリイカ",1],["サゴシ",1],["ブリ",1]],"1493":[["アオリイカ",4],["サゴシ",4],["アジ",1]],"1496":[["サッパ",1]],"1502":[["セイゴ（スズキ）",1],["セイゴ（タイリクスズキ）",1],["ハマチ",1]],"1505":[["エソ",3],["カマス",2],["アジ",1]],"1511":[["アオリイカ",2],["サゴシ",2],["ブリ",1]],"1522":[["アジ",1]],"1524":[["サゴシ",1],["サワラ",1]],"1525":[["アオリイカ",3],["アジ",1]],"1527":[["ブラックバス",1]],"1528":[["スモールマウスバス",1]],"1534":[["メッキ",1]],"1535":[["アオリイカ",1],["オオモンハタ",1],["スマガツオ",1]],"1536":[["エソ",1],["ホウボウ",1]],"1540":[["スズキ",3],["サゴシ",1]],"1543":[["アオリイカ",6],["アイゴ",1],["アジ",1]],"1548":[["スズキ",3],["アジ",2],["カサゴ",1]],"1549":[["アジ",1],["ハマチ",1]],"1551":[["アオリイカ",2]],"1553":[["アジ",1]],"1556":[["ブラックバス",1]],"1557":[["アジ",1],["ヒラメ",1]],"1559":[["アジ",1]],"1561":[["ツバス",2],["カマス",1],["ソゲ",1]],"1562":[["カサゴ",1]],"1565":[["アオハタ",1],["キジハタ",1]],"1572":[["アオリイカ",1]],"1574":[["サワラ",1],["ハマチ",1]],"1576":[["アジ",2],["エソ",1]],"1578":[["アイゴ",1],["アオリイカ",1]],"1580":[["カマス",1],["クロダイ",1],["マアジ",1]],"1581":[["サゴシ",1]],"1582":[["ブラックバス",1]],"1586":[["クロホシイシモチ",1],["コロダイ",1]],"1587":[["ブラックバス",2]],"1592":[["ヒラメ",1],["ワラサ",1]],"1596":[["カワハギ",2],["マダイ",1],["メジロ",1]],"1603":[["アオリイカ",3],["サゴシ",2],["イカ",1]],"1605":[["カツオ",1],["ギンガメアジ",1]],"1606":[["アオリイカ",1],["モンゴウイカ",1]],"1611":[["サゴシ",2],["エソ",1],["サバ",1]],"1613":[["アオリイカ",1],["ハマチ",1]],"1614":[["キス",1],["ヒラメ",1]],"1615":[["サバ",4],["アジ",3],["ハマチ",1]],"1617":[["スズキ",2],["タチウオ",2],["アカエイ",1]],"1619":[["アジ",1],["サゴシ",1]],"1623":[["ブラックバス",1]],"1626":[["ヒラマサ",3],["カンパチ",1],["シイラ",1]],"1627":[["アオリイカ",2],["アナハゼ",1],["ヒラメ",1]],"1631":[["クロダイ",1],["ヒラ",1]],"1632":[["ニゴイ",1]],"1633":[["アオリイカ",1],["エソ",1],["ツバイソ",1]],"1641":[["アジ",1],["サゴシ",1],["ネリゴ",1]],"1646":[["アジ",2],["タイ",1],["メバル",1]],"1648":[["アオリイカ",1],["サゴシ",1],["ミノカサゴ",1]],"1652":[["アオリイカ",3],["スズキ",1],["マゴチ",1]],"1654":[["ブラックバス",1]],"1657":[["ブラックバス",1]],"1658":[["カマス",2],["スズキ",2]],"1659":[["フナ",3],["コイ",2],["アメリカナマズ",1]],"1663":[["カマス",1]],"1667":[["アオリイカ",1],["アジ",1]],"1669":[["アジ",2],["マゴチ",1]],"1671":[["ソゲ",1]],"1673":[["サゴシ",1],["サバ",1],["タチウオ",1]],"1674":[["カワハギ",1]],"1679":[["サワラ",1],["ハマチ",1],["ブリ",1]],"1682":[["ブラックバス",1]],"1683":[["スズキ",1]],"1684":[["ブラックバス",9],["ブルーギル",1]],"1688":[["アジ",4],["アオリイカ",2],["カマス",2]],"1697":[["アオリイカ",1],["スズキ",1]],"1703":[["ブラックバス",3]],"1704":[["マダコ",1]],"1705":[["セイゴ（ヒラスズキ）",1],["ヒラメ",1],["マゴチ",1]],"1707":[["アイナメ",2],["フグ",2],["クジメ",1]],"1714":[["アオリイカ",1],["カサゴ",1],["ブリ",1]],"1717":[["スズキ",3],["サバ",1],["セイゴ（ヒラスズキ）",1]],"1721":[["ブラックバス",2],["ナマズ",1]],"1730":[["マハゼ",1]],"1732":[["ヒラメ",3],["ソゲ",2],["メッキ",2]],"1735":[["スズキ",4],["アジ",3],["タチウオ",2]],"1739":[["ミナミマゴチ",1]],"1742":[["ブラックバス",1],["マゴチ",1]],"1743":[["アオリイカ",5],["イサキ",1]],"1756":[["マゴチ",1]],"1758":[["スズキ",2],["タチウオ",2],["クロダイ",1]],"1764":[["サヨリ",1]],"1766":[["アオリイカ",1],["アジ",1],["キジハタ",1]],"1768":[["ソゲ",6],["タチウオ",4],["シタビラメ",2]],"1777":[["アナゴ",1],["ウマヅラハギ",1],["サゴシ",1]],"1779":[["ネリゴ",1]],"1782":[["アジ",1],["アナゴ",1],["ウロハゼ",1]],"1787":[["スズキ",1],["ハマチ",1]],"1790":[["サバ",1],["メバル",1]],"1791":[["クロダイ",1],["セイゴ（スズキ）",1],["ソゲ",1]],"1792":[["サクラマス",1]],"1793":[["カサゴ",2],["アイゴ",1],["アオリイカ",1]],"1797":[["クロダイ",1],["メジロ",1]],"1798":[["サゴシ",2],["タチウオ",2],["キス",1]],"1800":[["タケノコメバル",4],["カサゴ",1]],"1802":[["アジ",1]],"1805":[["アジ",1]],"1810":[["クロダイ",1]],"1813":[["ヒラメ",2],["アジ",1],["クロソイ",1]],"1818":[["アカカマス",1],["クロダイ",1],["ヒイラギ",1]],"1819":[["スズキ",2],["ニゴイ",1],["フッコ（スズキ）",1]],"1821":[["アジ",1],["カサゴ",1],["フグ",1]],"1822":[["アジ",5],["アオリイカ",2],["キビレ",1]],"1823":[["アジ",4],["カワハギ",1],["ショウサイフグ",1]],"1825":[["イサキ",1],["ハマチ",1]],"1831":[["アジ",1],["ヤズ",1]],"1832":[["アオリイカ",3],["クエ",1]],"1837":[["アカササノハベラ",1]],"1838":[["カマス",1],["マゴチ",1]],"1844":[["カワハギ",1]],"1848":[["ヒラメ",1]],"1855":[["スズキ",4]],"1864":[["ヒラメ",1]],"1866":[["スズキ",1]],"1867":[["アカエイ",1]],"1869":[["マハゼ",1]],"1872":[["イラ",1]],"1873":[["アオリイカ",1],["アジ",1],["イタチウオ",1]],"1874":[["ブラックバス",2]],"1876":[["アオリイカ",1],["キジハタ",1]],"1877":[["スズキ",1],["セイゴ（スズキ）",1]],"1879":[["スズキ",6]],"1884":[["ラージマウスバス",1]],"1889":[["アオリイカ",1]],"1892":[["ソゲ",1],["ヒラメ",1]],"1895":[["ラージマウスバス",1]],"1898":[["セイゴ（スズキ）",2]],"1899":[["スズキ",3],["マゴチ",2],["ワタリガニ",1]],"1902":[["アカカマス",1],["アジ",1],["ガンド",1]],"1907":[["シロメバル",2],["メバル",2],["アイナメ",1]],"1911":[["ソゲ",1],["ヒラメ",1],["フッコ（スズキ）",1]],"1915":[["アイナメ",1]],"1922":[["ヒメマス",2]],"1924":[["ブラックバス",1]],"1928":[["スズキ",2],["ラージマウスバス",1]],"1945":[["エソ",1],["カンパチ",1],["ショゴ",1]],"1947":[["アオリイカ",1],["カサゴ",1]],"1948":[["アオリイカ",1]],"1951":[["ハマチ",4],["ヤズ",2],["エソ",1]],"1953":[["カサゴ",1]],"1955":[["ブラックバス",2]],"1956":[["アオリイカ",1],["エソ",1],["キジハタ",1]],"1960":[["スズキ",2]],"1963":[["アメリカナマズ",1]],"1968":[["アオリイカ",1],["メジナ",1]],"1970":[["アオリイカ",4]],"1975":[["カンパチ",1]],"1976":[["セイゴ（ヒラスズキ）",1],["タチウオ",1],["マゴチ",1]],"1977":[["シタビラメ",1]],"1981":[["スズキ",2],["タチウオ",1]],"1993":[["イナダ",1],["スズキ",1]],"1996":[["ヒラマサ",1]],"1998":[["ワカサギ",1]],"2010":[["タチウオ",1]],"2013":[["アオリイカ",1],["ウグイ",1],["サヨリ",1]],"2015":[["アジ",3],["セイゴ（スズキ）",1]],"2029":[["オイカワ",1],["ブラックバス",1]],"2034":[["ラージマウスバス",1]],"2035":[["カライワシ",1],["ギンガメアジ",1],["タイワンカマス",1]],"2036":[["サゴシ",1]],"2037":[["コウイカ",2]],"2041":[["スズキ",2],["アオリイカ",1]],"2043":[["マダイ",5],["アオリイカ",1],["タイ",1]],"2044":[["メジナ",1]],"2047":[["ウルメイワシ",1]],"2051":[["アニュラーシーブリーム",1],["スズキ",1],["ソゲ",1]],"2052":[["ネリゴ",1],["ブリ",1]],"2053":[["スズキ",1],["マゴチ",1]],"2057":[["サワラ",1]],"2063":[["サバ",1],["タコ",1]],"2066":[["スズキ",1],["チャイロマルハタ",1]],"2071":[["ニジマス",4]],"2074":[["アオリイカ",2],["ハガツオ",1],["ミナミハタンポ",1]],"2088":[["ネイリ",1],["メッキ",1],["ワカシ",1]],"2101":[["アオリイカ",1]],"2107":[["ヒラメ",1],["マゴチ",1]],"2108":[["サワラ",1]],"2109":[["ブラックバス",4]],"2111":[["マダイ",2],["アジ",1],["クロダイ",1]],"2121":[["アイゴ",2],["カサゴ",1],["ムツ",1]],"2124":[["アオリイカ",3]],"2126":[["ブラックバス",2]],"2138":[["アオリイカ",1],["オオモンハタ",1],["ネリゴ",1]],"2140":[["メアジ",1]],"2141":[["ブラックバス",3]],"2142":[["サゴシ",1]],"2148":[["マアナゴ",1],["マダイ",1]],"2149":[["ブラックバス",4]],"2151":[["ママカリ",1]],"2161":[["クロダイ",1]],"2167":[["スズキ",1]],"2168":[["ラージマウスバス",6],["ブルーギル",4],["スモールマウスバス",1]],"2172":[["ワカサギ",1]],"2180":[["スズキ",1],["ソゲ",1],["ヒラメ",1]],"2182":[["ヒラメ",1],["ブラックバス",1]],"2187":[["シオ",1]],"2198":[["アオリイカ",1],["ヤズ",1]],"2204":[["サケ",1]],"2206":[["スズキ",9],["コノシロ",1]],"2208":[["アジ",1],["カサゴ",1],["セイゴ（ヒラスズキ）",1]],"2216":[["エソ",3],["ハマチ",1]],"2221":[["イナダ",2]],"2225":[["アジ",1],["エソ",1],["サゴシ",1]],"2227":[["ブラックバス",1]],"2236":[["ブラックバス",1]],"2241":[["アオリイカ",2]],"2264":[["エソ",1]],"2266":[["アオリイカ",1]],"2281":[["ヒラマサ",1],["ヤズ",1]],"2283":[["ブラックバス",1]],"2284":[["スズキ",2],["ワラサ",2],["ハマチ",1]],"2295":[["アオリイカ",1]],"2296":[["エソ",1],["サゴシ",1],["ヤズ",1]],"2297":[["ヒイカ",1],["マアジ",1]],"2307":[["ラージマウスバス",1]],"2309":[["アジ",1]],"2310":[["アオリイカ",2],["スズキ",1]],"2312":[["ウグイ",1],["ニゴイ",1]],"2364":[["アカメフグ",1],["シタビラメ",1],["ソゲ",1]],"2370":[["キジハタ",1],["ヒラマサ",1]],"2376":[["タチウオ",2],["アジ",1]],"2378":[["アオリイカ",4],["ワラサ",1]],"2401":[["カサゴ",1]],"2419":[["アオリイカ",2]],"2433":[["アオリイカ",1],["クロダイ",1],["タイ",1]],"2440":[["アイナメ",2],["アジ",1],["クロソイ",1]],"2444":[["スズキ",8],["カサゴ",1],["タチウオ",1]],"2449":[["アジ",1]],"2470":[["アジ",1],["クロソイ",1],["サゴシ",1]],"2485":[["フグ",2],["イナダ",1],["コバンアジ",1]],"2493":[["ブラックバス",2]],"2495":[["サッパ",1],["ボラ",1]],"2501":[["ウミタナゴ",1]],"2502":[["マゴチ",1]],"2504":[["スズキ",2]],"2507":[["アオリイカ",1],["ヤズ",1]],"2509":[["セイゴ（スズキ）",1]],"2513":[["ブラックバス",1]],"2515":[["オオモンハタ",1]],"2516":[["アジ",1],["コウイカ",1],["スズキ",1]],"2517":[["アイナメ",1],["イナダ",1],["スルメイカ",1]],"2524":[["タチウオ",2],["サワラ",1],["スズメダイ",1]],"2546":[["ブラックバス",1]],"2547":[["スズキ",3],["アオリイカ",1],["コゾクラ",1]],"2559":[["アジ",2]],"2564":[["アジ",1],["フエフキダイ",1],["メアジ",1]],"2572":[["スズキ",3]],"2573":[["サゴシ",1]],"2607":[["ニジマス",1]],"2612":[["アジ",2],["スズキ",1],["マアナゴ",1]],"2642":[["アジ",3],["アオリイカ",1],["タコ",1]],"2648":[["アオリイカ",1]],"2649":[["セイゴ（ヒラスズキ）",1],["ヒラメ",1],["マゴチ",1]],"2650":[["アメマス",1]],"2651":[["カサゴ",1]],"2652":[["アオリイカ",1],["アカカマス",1],["カンパチ",1]],"2659":[["イナダ",2],["ニベ",1],["ヒラスズキ",1]],"2667":[["イワシ",1],["スマガツオ",1],["タチウオ",1]],"2672":[["ブラックバス",10]],"2675":[["スズキ",3],["コノシロ",1],["フッコ（ヒラスズキ）",1]],"2681":[["アオリイカ",2],["アジ",1],["カマス",1]],"2683":[["エソ",1]],"2685":[["カワハギ",1],["トウゴロウイワシ",1]],"2690":[["アジ",1],["シイラ",1]],"2715":[["カマス",1],["サワラ",1],["タチウオ",1]],"2721":[["サザナミフグ",1]],"2731":[["ツバス",1],["ハマチ",1]],"2735":[["ニジマス",1]],"2736":[["アオリイカ",1]],"2760":[["オオモンハタ",1]],"2762":[["スズキ",1]],"2824":[["メバル",1]],"2838":[["ハマチ",1]],"2934":[["スズキ",1]],"2941":[["スズキ",1],["ブラックバス",1],["ライギョ",1]],"2947":[["アオリイカ",1]],"3005":[["スマガツオ",1]],"3008":[["アオリイカ",1],["イサキ",1]],"3079":[["スズキ",1],["ヒラメ",1],["フッコ（スズキ）",1]],"3107":[["アオリイカ",1],["フクラギ",1]],"3176":[["ラージマウスバス",2]],"3217":[["アオリイカ",1]],"3232":[["マダイ",1]],"3268":[["アオリイカ",1]],"3300":[["アジ",1]],"3347":[["スズキ",2],["フクラギ",1]],"3420":[["アオリイカ",1],["キジハタ",1]],"3494":[["アオリイカ",1]],"3536":[["ブラックバス",1]],"3978":[["カサゴ",1]],"3982":[["サゴシ",1],["タチウオ",1],["ヒラメ",1]],"3983":[["タチウオ",4],["アジ",1],["イナダ",1]],"3985":[["エソ",2],["サゴシ",1],["サヨリ",1]],"3994":[["マメイカ",3],["クロソイ",1],["サバ",1]],"3995":[["サゴシ",9],["メジロ",6],["サバ",2]],"3997":[["ソゲ",1]],"4000":[["タチウオ",6],["スズキ",2],["メッキ",2]],"4004":[["タチウオ",5],["カマス",1]],"4005":[["イシモチ",1],["イワシ",1],["シロメバル",1]],"4006":[["アジ",1],["スズキ",1],["ブリ",1]],"4008":[["キス",1],["フグ",1],["メゴチ",1]],"4010":[["アジ",1],["イナダ",1]],"4012":[["アジ",1],["タチウオ",1],["ヒラメ",1]],"4013":[["クロソイ",1]],"4014":[["カサゴ",2],["タチウオ",1]],"4016":[["タチウオ",2],["スズキ",1]],"4025":[["マイワシ",2],["アジ",1],["イナダ",1]],"4032":[["スズキ",1],["ヒラメ",1]],"4045":[["アカカマス",1],["カマス",1],["タイ",1]],"4046":[["アジ",2],["ヤズ",2],["アオリイカ",1]],"4061":[["イナダ",1]],"4094":[["サヨリ",1]],"4191":[["アオリイカ",1]]}