{"2":[["スズキ",2],["アジ",1],["マダイ",1]],"3":[["スズキ",2]],"4":[["アジ",2],["ウミタナゴ",2],["キジハタ",1]],"5":[["ウツボ",1],["サバ",1]],"6":[["スズキ",9],["アジ",4],["セイゴ（スズキ）",2]],"7":[["アジ",1],["タイ",1]],"10":[["スズキ",6],["メバル",6],["アジ",5]],"11":[["アオリイカ",1]],"13":[["アジ",1]],"14":[["エゾメバル",2],["シマソイ",2]],"16":[["コイ",2],["スモールマウスバス",1]],"18":[["アジ",8],["スズキ",7],["アオリイカ",5]],"20":[["スズキ",4]],"22":[["スズキ",4],["アジ",1],["カサゴ",1]],"23":[["スズキ",5],["マダイ",3],["クロダイ",2]],"24":[["アナゴ",1],["ドチザメ",1]],"26":[["エイ",1]],"33":[["アジ",3],["セイゴ（スズキ）",1]],"34":[["カジカ",1],["クロソイ",1],["シロメバル",1]],"35":[["アジ",1]],"36":[["クロソイ",1],["ヒイカ",1]],"37":[["ワカサギ",2]],"39":[["アジ",34],["カサゴ",20],["メバル",8]],"40":[["アジ",1],["カサゴ",1],["ヒガンフグ",1]],"42":[["スズキ",6],["ニゴイ",1]],"44":[["スズキ",15],["カサゴ",8],["コノシロ",2]],"45":[["アオリイカ",9],["メバル",9],["アジ",3]],"46":[["タケノコメバル",7],["カサゴ",2],["シロメバル",1]],"47":[["クロソイ",1],["ハタハタ",1],["マゾイ",1]],"49":[["アジ",1]],"51":[["フナ",1],["ブラックバス",1],["ラージマウスバス",1]],"52":[["ブラックバス",1]],"55":[["キジハタ",9],["アジ",5],["メバル",3]],"56":[["セイゴ（タイリクスズキ）",1]],"57":[["アイナメ",2],["クロソイ",2]],"58":[["アジ",1],["カサゴ",1]],"61":[["スズキ",6],["メバル",3],["クロソイ",1]],"62":[["クロダイ",1],["チンチン",1]],"63":[["アジ",5],["メバル",5],["アカメバル",2]],"64":[["アジ",1],["カサゴ",1],["セイゴ（スズキ）",1]],"65":[["クロダイ",1],["スズキ",1]],"67":[["クロソイ",1],["マイワシ",1]],"68":[["アジ",3],["サバ",1],["タチウオ",1]],"70":[["カマス",5],["タチウオ",2],["カサゴ",1]],"72":[["アジ",13],["アオリイカ",5],["ヒイカ",2]],"73":[["メバル",4],["アジ",2],["カサゴ",1]],"74":[["アジ",2],["カサゴ",1],["セイゴ（スズキ）",1]],"75":[["ヤリイカ",9],["イカ",7],["クロソイ",6]],"76":[["マアジ",9],["スズキ",3],["アオリイカ",1]],"77":[["アジ",5],["シロメバル",4],["マアジ",3]],"78":[["クロダイ",1]],"79":[["ヤリイカ",12],["イカ",10],["クロソイ",10]],"80":[["スズキ",5],["クロダイ",2]],"82":[["カサゴ",2],["マダイ",2],["アオリイカ",1]],"83":[["アジ",6],["メバル",3],["ブリ",2]],"84":[["アジ",2],["カサゴ",1],["メバル",1]],"86":[["スズキ",3]],"87":[["メバル",1]],"93":[["アジ",3],["マアジ",1]],"94":[["カサゴ",8],["メバル",2],["キジハタ",1]],"95":[["アイナメ",4]],"96":[["スズキ",7]],"97":[["スズキ",2],["クロダイ",1],["シロメバル",1]],"99":[["カサゴ",5],["アジ",1],["アナゴ",1]],"100":[["スズキ",27],["セイゴ（スズキ）",4],["メバル",4]],"103":[["アジ",11],["ヒイカ",9],["メバル",4]],"104":[["アジ",3],["アオリイカ",2],["メッキ",1]],"105":[["メバル",2],["アイナメ",1],["クロソイ",1]],"106":[["クロダイ",2]],"107":[["カサゴ",3],["スズキ",1],["セイゴ（スズキ）",1]],"108":[["スズキ",1]],"110":[["ヒラマサ",1],["ブリ",1]],"111":[["スズキ",8],["セイゴ（スズキ）",2],["ヒラメ",2]],"112":[["セイゴ（スズキ）",1]],"114":[["マダイ",1]],"117":[["アジ",3],["カサゴ",2],["ブリ",2]],"119":[["アジ",23],["マアジ",7],["メバル",3]],"123":[["アジ",8],["マアジ",4],["アオリイカ",2]],"124":[["アイナメ",2],["マハゼ",2],["クロソイ",1]],"125":[["メバル",5],["カサゴ",2],["タケノコメバル",2]],"126":[["キンメダイ",4],["アジ",1],["キハダマグロ",1]],"127":[["スズキ",3],["クロダイ",2],["キビレ",1]],"128":[["アオリイカ",1]],"129":[["アオリイカ",4],["アジ",2],["アカイカ",1]],"132":[["アナゴ",1],["セイゴ（スズキ）",1]],"135":[["カサゴ",2],["スズキ",1],["タケノコメバル",1]],"136":[["カサゴ",1],["クロダイ",1]],"138":[["アオリイカ",1],["ギンガメアジ",1],["ヤイトハタ",1]],"140":[["クロダイ",1],["ブリ",1],["マトウダイ",1]],"143":[["タチウオ",12],["アジ",7],["カサゴ",6]],"145":[["アジ",4],["マアジ",4],["メバル",2]],"146":[["アジ",2],["クロソイ",2],["クロダイ",1]],"147":[["マハゼ",1]],"149":[["アジ",6],["カサゴ",2],["コウイカ",1]],"151":[["ニシン",3],["アイナメ",2],["マハゼ",1]],"152":[["アオリイカ",3],["アジ",3],["メジナ",3]],"153":[["アジ",6],["カマス",4],["キス",2]],"156":[["アジ",4],["カサゴ",2],["マアジ",1]],"157":[["スズキ",3],["アジ",2],["マアジ",2]],"158":[["スズキ",1]],"159":[["アジ",2],["カサゴ",2],["タケノコメバル",1]],"160":[["スズキ",16],["カサゴ",14],["アジ",13]],"161":[["アジ",1]],"162":[["メバル",2]],"163":[["カレイ",1],["コマイ",1]],"165":[["アジ",2],["フッコ（スズキ）",1],["マハゼ",1]],"166":[["キビレ",3],["クロダイ",1],["シロメバル",1]],"168":[["スズキ",3],["キビレ",1]],"169":[["カサゴ",5],["サバ",1]],"171":[["スズキ",5],["コイ",1]],"172":[["スズキ",11],["アカエイ",1],["セイゴ（スズキ）",1]],"174":[["アジ",6],["カサゴ",2],["メバル",2]],"175":[["タチウオ",2],["カサゴ",1],["クサフグ",1]],"178":[["スズキ",11],["クロソイ",2],["アイナメ",1]],"183":[["スズキ",2]],"185":[["アジ",1],["メバル",1]],"186":[["クロソイ",1],["タケノコメバル",1],["タコ",1]],"189":[["アジ",6],["イシモチ",2],["スズキ",2]],"191":[["アジ",5],["クロダイ",2],["シロメバル",2]],"192":[["ワカサギ",1]],"193":[["カサゴ",1]],"194":[["アオリイカ",4],["タチウオ",2],["アジ",1]],"197":[["アジ",1],["メバル",1]],"200":[["アジ",10],["カサゴ",3],["タケノコメバル",2]],"201":[["スズキ",1]],"202":[["アジ",1],["カサゴ",1],["ソゲ",1]],"203":[["スズキ",6],["アジ",1]],"204":[["シタビラメ",1],["スズキ",1],["セイゴ（スズキ）",1]],"206":[["アジ",1],["カサゴ",1],["メバル",1]],"210":[["アオリイカ",2],["アオチビキ",1],["クロダイ",1]],"212":[["キジハタ",2],["カサゴ",1],["タケノコメバル",1]],"214":[["クロダイ",10],["スズキ",4],["ウナギ",1]],"215":[["アオリイカ",7],["アカカマス",1],["オオニベ",1]],"218":[["キビレ",2],["スズキ",2],["アナゴ",1]],"220":[["キジハタ",1],["スズキ",1]],"222":[["クロソイ",2]],"223":[["カサゴ",1]],"227":[["スズキ",14],["マハゼ",1]],"228":[["カサゴ",3],["メバル",1]],"229":[["ラージマウスバス",1]],"231":[["ハタハタ",3],["クロソイ",2],["スズキ",2]],"232":[["カサゴ",1],["サバ",1],["シロメバル",1]],"234":[["アオリイカ",2],["アジ",1],["イッテンフエダイ",1]],"236":[["ニシン",2],["クロソイ",1]],"238":[["スズキ",2]],"239":[["メバル",10],["カサゴ",7],["スズキ",6]],"241":[["スズキ",1]],"247":[["カサゴ",1],["メバル",1]],"248":[["クロダイ",1]],"249":[["ケンサキイカ",6],["メバル",6],["カサゴ",4]],"252":[["タチウオ",23],["カスザメ",3],["スズキ",3]],"254":[["スズキ",4],["アジ",1],["イラ",1]],"255":[["タチウオ",1]],"256":[["タチウオ",1]],"258":[["スズキ",1],["セイゴ（ヒラスズキ）",1]],"259":[["アジ",4],["ヒラスズキ",1]],"260":[["スズキ",7],["アジ",6],["セイゴ（スズキ）",5]],"263":[["カサゴ",1],["マハタ",1]],"265":[["カサゴ",2],["タケノコメバル",2],["アジ",1]],"267":[["スズキ",3],["カサゴ",2],["アオリイカ",1]],"268":[["タチウオ",3],["クロタチカマス",2],["アオリイカ",1]],"270":[["カレイ",3],["スズキ",2],["ヒイカ",2]],"274":[["スズキ",4]],"276":[["セイゴ（スズキ）",1]],"278":[["セイゴ（ヒラスズキ）",2],["クロダイ",1],["セイゴ（スズキ）",1]],"282":[["スズキ",5],["セイゴ（スズキ）",1],["マハゼ",1]],"287":[["キンメダイ",1],["ヒラスズキ",1],["マアジ",1]],"289":[["メバル",4],["アメマス",1],["クロソイ",1]],"294":[["カサゴ",6],["アジ",4],["タケノコメバル",2]],"301":[["カサゴ",6],["アジ",4],["イトヒキアジ",1]],"302":[["カサゴ",6],["アジ",2],["メバル",2]],"306":[["ショウサイフグ",1],["ナマズ",1]],"310":[["アジ",5],["アオリイカ",3],["スズキ",3]],"312":[["アイナメ",5],["クロソイ",4],["メバル",4]],"313":[["スズキ",1]],"317":[["メバル",7],["アジ",4],["カサゴ",1]],"318":[["アオリイカ",1],["カサゴ",1]],"320":[["アジ",1],["クロダイ",1]],"321":[["ソイ",2],["カサゴ",1],["スズキ",1]],"322":[["アオリイカ",1],["カサゴ",1],["ヒラスズキ",1]],"323":[["メバル",6],["ドンコ",2],["アイナメ",1]],"324":[["スズキ",4]],"325":[["カサゴ",13],["アジ",6],["スズキ",4]],"326":[["カサゴ",1]],"327":[["アジ",2],["カサゴ",1],["タチウオ",1]],"328":[["ヒラメ",1]],"329":[["スズキ",4],["マハゼ",4],["メバル",4]],"330":[["クロソイ",1],["マゾイ",1]],"331":[["ソイ",2],["クジメ",1]],"333":[["カサゴ",1],["キジハタ",1],["クロダイ",1]],"334":[["ブラックバス",1]],"336":[["マハゼ",3],["スズキ",1]],"337":[["アイナメ",6],["クロソイ",4],["メバル",3]],"338":[["アジ",1]],"339":[["カサゴ",6],["カマス",4],["タチウオ",4]],"340":[["メバル",3],["カサゴ",1]],"341":[["アジ",2],["アオリイカ",1],["イカ",1]],"343":[["アカハタ",1]],"352":[["アジ",6],["スズキ",2],["メバル",2]],"353":[["ブラックバス",6],["ブルーギル",1]],"354":[["アオリイカ",3],["カマス",2],["イカ",1]],"356":[["アイナメ",11],["セイゴ（スズキ）",2],["マアナゴ",1]],"357":[["スズキ",26],["カニ",1]],"358":[["スズキ",1]],"359":[["ギンガメアジ",2],["アカイカ",1],["イナダ",1]],"362":[["オニオコゼ",1],["クロメバル",1]],"364":[["アオリイカ",1],["キジハタ",1],["クロダイ",1]],"366":[["ワカサギ",4],["ブラックバス",2],["ニジマス",1]],"368":[["ニジマス",8]],"370":[["スルメイカ",1],["ドンコ",1]],"371":[["アオリイカ",2],["ゴマサバ",1]],"373":[["アジ",4],["マアジ",2],["ウスメバル",1]],"374":[["メバル",11],["スズキ",5],["タケノコメバル",3]],"375":[["アオリイカ",1],["アジ",1],["チャイロマルハタ",1]],"376":[["カサゴ",6],["タケノコメバル",4],["シロメバル",3]],"377":[["スズキ",6],["アジ",2],["クロダイ",2]],"384":[["ケンサキイカ",16],["アオリイカ",1],["カワハギ",1]],"389":[["アジ",2],["マダコ",2],["カサゴ",1]],"392":[["マダイ",1]],"393":[["エゾメバル",2],["シマゾイ",2],["アイナメ",1]],"394":[["アオリイカ",2],["タチウオ",1]],"395":[["ブリ",1]],"398":[["スズキ",12],["ニホンウナギ",1]],"399":[["アオリイカ",1]],"400":[["カサゴ",1],["キス",1]],"401":[["マアナゴ",1]],"403":[["スズキ",6],["カサゴ",5],["アナゴ",3]],"404":[["カサゴ",11],["スズキ",8],["メバル",6]],"406":[["ウロハゼ",1],["カタクチイワシ",1],["キス",1]],"407":[["アジ",3],["コウイカ",1],["スズキ",1]],"408":[["クロソイ",5],["メバル",4],["アイナメ",3]],"412":[["タチウオ",2],["シタビラメ",1],["スズキ",1]],"413":[["ハネ（ヒラスズキ）",1]],"414":[["シタビラメ",1],["ヒラメ",1],["ボラ",1]],"418":[["スズキ",49],["セイゴ（スズキ）",1],["マゴチ",1]],"420":[["カサゴ",12],["アジ",3],["タチウオ",3]],"423":[["カサゴ",2],["セイゴ（スズキ）",2],["タケノコメバル",1]],"424":[["メバル",6],["アジ",4],["スズキ",3]],"435":[["メバル",1]],"439":[["アジ",1]],"441":[["シロメバル",1],["マゴチ",1]],"443":[["ワカサギ",1]],"444":[["アジ",1]],"445":[["コイ",1]],"446":[["アジ",5],["メバル",4],["クロメバル",2]],"448":[["ソイ",1]],"451":[["イワナ",1]],"454":[["アオリイカ",1],["アジ",1],["イサキ",1]],"456":[["シロメバル",3],["アイナメ",2],["クロソイ",2]],"458":[["オウゴンムラソイ",2],["クロソイ",1],["シマゾイ",1]],"459":[["アジ",1],["ソイ",1]],"460":[["アジ",1]],"461":[["アジ",12],["スズキ",2],["タケノコメバル",1]],"463":[["クエ",1]],"464":[["セイゴ（スズキ）",2]],"468":[["アジ",9],["アイナメ",2],["アカメバル",2]],"472":[["ハチガラ",1]],"474":[["スズキ",1]],"475":[["スズキ",3]],"477":[["カサゴ",2],["アジ",1],["アナゴ",1]],"481":[["メバル",2],["シロメバル",1]],"484":[["メバル",5],["ドンコ",4],["ヤリイカ",4]],"485":[["カサゴ",1],["セイゴ（スズキ）",1],["ヒイカ",1]],"488":[["スズキ",2]],"489":[["スズキ",4],["クロダイ",1]],"491":[["アオリイカ",1]],"492":[["アオリイカ",1],["カサゴ",1]],"498":[["クロダイ",1],["サゴシ",1],["サバ",1]],"502":[["スズキ",5]],"503":[["タイ",1],["ヒラメ",1],["ブリ",1]],"504":[["スズキ",4],["マルタウグイ",3],["クロダイ",2]],"506":[["ブラックバス",4]],"508":[["カサゴ",1],["ソイ",1],["マゴチ",1]],"510":[["ナマズ",2]],"512":[["タコ",1]],"514":[["ブラックバス",3]],"518":[["タマン",1]],"521":[["アジ",8],["メバル",2],["スズキ",1]],"523":[["クロソイ",3],["タケノコメバル",2],["カサゴ",1]],"524":[["テナガエビ",1]],"527":[["キジハタ",1],["メジナ",1]],"529":[["カサゴ",1],["クロソイ",1],["ヒラメ",1]],"531":[["アイナメ",2],["アナゴ",1],["サバ",1]],"532":[["マハゼ",1]],"535":[["カサゴ",8],["タケノコメバル",2],["メバル",2]],"538":[["タカノハダイ",1]],"540":[["ヒラメ",1]],"541":[["アオリイカ",1],["スズキ",1],["マトウダイ",1]],"542":[["スズキ",2]],"549":[["スズキ",3]],"550":[["アオリイカ",3],["ブダイ",1]],"552":[["アナゴ",1],["セイゴ（スズキ）",1]],"556":[["カサゴ",1]],"561":[["スズキ",2],["セイゴ（スズキ）",1]],"562":[["クロメバル",1],["シロメバル",1],["スズキ",1]],"564":[["ブラックバス",1]],"565":[["アジ",2],["カサゴ",1],["クロソイ",1]],"567":[["キビレ",1],["クロダイ",1],["スズキ",1]],"571":[["オオニベ",1]],"578":[["クロソイ",1],["スズキ",1]],"581":[["カマス",3],["スズキ",1],["セイゴ（スズキ）",1]],"584":[["クロソイ",2],["オウゴンムラソイ",1]],"586":[["カマス",1],["マアジ",1]],"590":[["メバル",1]],"591":[["カサゴ",1]],"597":[["スズキ",1],["ハタハタ",1]],"602":[["カサゴ",3],["アジ",1],["タケノコメバル",1]],"604":[["メバル",6],["カサゴ",5],["ダイナンアナゴ",2]],"606":[["アメマス",1]],"607":[["アジ",3]],"608":[["アジ",4],["アカカマス",1]],"609":[["メバル",2]],"611":[["アジ",2],["メバル",2],["マイワシ",1]],"617":[["アジ",1]],"622":[["セイゴ（ヒラスズキ）",1]],"623":[["アジ",5],["カサゴ",1],["サワラ",1]],"625":[["カサゴ",1]],"626":[["スズキ",3]],"628":[["アジ",1],["イセエビ",1],["クロソイ",1]],"631":[["アジ",1],["コウイカ",1],["メバル",1]],"633":[["タチウオ",14],["ヒラメ",2],["ボラ",1]],"636":[["アジ",1],["セイゴ（タイリクスズキ）",1],["ヒイカ",1]],"637":[["カサゴ",1],["スズメダイ",1],["ブリ",1]],"638":[["ゴンズイ",2],["アオリイカ",1],["アジ",1]],"639":[["イズカサゴ",1]],"641":[["セイゴ（スズキ）",2]],"643":[["シマスズキ",3]],"646":[["ヤリイカ",5],["メバル",4],["アイナメ",3]],"649":[["スズキ",7],["セイゴ（スズキ）",1]],"652":[["スズキ",1]],"653":[["カサゴ",1],["クロソイ",1]],"654":[["アジ",2],["カサゴ",1]],"655":[["アジ",10],["メバル",3],["マアジ",2]],"660":[["アオリイカ",10],["ヒラスズキ",3],["ヒラマサ",3]],"661":[["カサゴ",2],["スズキ",2],["タケノコメバル",2]],"664":[["ニジマス",1]],"665":[["アジ",6],["アオリイカ",3],["セイゴ（ヒラスズキ）",2]],"670":[["タケノコメバル",3],["クロソイ",2]],"677":[["スズキ",1]],"681":[["シロメバル",2],["メバル",2]],"682":[["カサゴ",1],["スズキ",1],["セイゴ（スズキ）",1]],"689":[["メバル",2],["シロメバル",1],["タケノコメバル",1]],"690":[["ヒラスズキ",1]],"691":[["クロダイ",1],["クロメバル",1]],"693":[["エイ",1],["スズキ",1]],"695":[["スズキ",6]],"697":[["カサゴ",3],["スズキ",3]],"699":[["クロダイ",3],["スズキ",2]],"705":[["クロムツ",1]],"707":[["メバル",3],["アナゴ",1],["キジハタ",1]],"708":[["スズキ",10],["セイゴ（スズキ）",3]],"709":[["シマアジ",1],["マアジ",1]],"710":[["サクラマス",1]],"712":[["スズキ",1]],"713":[["キビレ",1],["スズキ",1],["フッコ（スズキ）",1]],"717":[["スズキ",10],["カサゴ",2],["セイゴ（スズキ）",2]],"721":[["メジナ",1]],"724":[["セイゴ（スズキ）",5],["アジ",2],["カサゴ",2]],"727":[["スズキ",1]],"728":[["メバル",5],["イカ",3],["クロソイ",3]],"731":[["アオリイカ",2]],"732":[["シロメバル",3],["スズキ",3],["カサゴ",1]],"735":[["サゴシ",4],["エソ",1],["オオモンハタ",1]],"737":[["アジ",2],["カサゴ",2],["キビレ",1]],"738":[["ヒラメ",1]],"742":[["カサゴ",1]],"744":[["イワナ",1]],"745":[["クロダイ",1],["ヒラメ",1]],"746":[["キビレ",1]],"749":[["アオリイカ",2],["スルメイカ",2],["カサゴ",1]],"750":[["クロダイ",2]],"752":[["クロソイ",1]],"754":[["クロダイ",1],["スズキ",1]],"756":[["アイナメ",1]],"757":[["アオリイカ",5]],"758":[["フッコ（スズキ）",1]],"759":[["スズキ",11],["マアジ",6],["カサゴ",5]],"762":[["キダイ",1],["メバル",1]],"764":[["クロソイ",2]],"765":[["モクズガニ",1]],"766":[["クロダイ",5],["メッキ",3],["メジナ",2]],"770":[["アジ",2],["マハタ",1]],"776":[["アオメバル",1],["スズキ",1],["メバル",1]],"777":[["スズキ",1],["タチウオ",1],["ヒラメ",1]],"787":[["ニシン",4],["チカ",1]],"789":[["アカカマス",1]],"790":[["ブラックバス",1]],"792":[["スズキ",8]],"793":[["アジ",1],["セイゴ（スズキ）",1],["マゴチ",1]],"797":[["スズキ",2]],"799":[["スズキ",2]],"800":[["メバル",2]],"803":[["マアジ",2],["メバル",1]],"804":[["アオリイカ",4],["アカイカ",1],["イサキ",1]],"812":[["アジ",1],["シロメバル",1],["メバル",1]],"813":[["ソイ",1],["メバル",1]],"821":[["キビレ",5],["クロダイ",3]],"824":[["アジ",23],["ギンガメアジ",3],["マアジ",3]],"830":[["スズキ",9],["セイゴ（スズキ）",3],["アジ",1]],"831":[["オオニベ",1]],"835":[["イナダ",1]],"837":[["アオリイカ",1]],"839":[["クロダイ",1]],"841":[["カサゴ",1],["タケノコメバル",1],["ボラ",1]],"842":[["スズキ",1]],"845":[["アオリイカ",7],["メッキ",1]],"846":[["スズキ",14],["クロダイ",2],["コイ",1]],"853":[["ソゲ",1],["タチウオ",1],["ヒラメ",1]],"855":[["カマス",2],["アカカマス",1],["シリヤケイカ",1]],"857":[["クロダイ",1]],"861":[["アオリイカ",1],["オオモンハタ",1]],"863":[["カサゴ",1],["シロメバル",1]],"873":[["スズキ",4],["カサゴ",1],["マハゼ",1]],"879":[["ブリ",2],["アジ",1],["イワシ",1]],"884":[["スズキ",1]],"885":[["アジ",2],["カサゴ",1]],"886":[["マダイ",1],["メバル",1]],"887":[["アジ",1]],"890":[["カサゴ",5],["メバル",4],["タケノコメバル",2]],"894":[["アジ",2],["カサゴ",1],["キジハタ",1]],"897":[["スズキ",1]],"898":[["スズキ",1]],"899":[["アジ",6],["カサゴ",2],["シロメバル",1]],"900":[["マハゼ",3]],"901":[["アジ",1],["カサゴ",1]],"902":[["タイ",1]],"904":[["アジ",7]],"906":[["クロソイ",1],["シマソイ",1],["マメイカ",1]],"907":[["ヒラスズキ",1],["マアジ",1]],"908":[["クロアナゴ",1],["チイチイイカ",1]],"909":[["カサゴ",10],["メバル",3],["カタクチイワシ",1]],"911":[["スズキ",7],["クロダイ",1],["ボラ",1]],"912":[["ウツボ",1]],"914":[["セイゴ（スズキ）",2],["アジ",1],["メバル",1]],"915":[["カサゴ",2],["カマス",2],["キンメダイ",2]],"925":[["キジハタ",3],["スズキ",3],["アジ",1]],"933":[["スズキ",1]],"934":[["キジハタ",1]],"938":[["カサゴ",1]],"939":[["スズキ",1]],"941":[["キジハタ",1]],"942":[["ニジマス",1]],"947":[["コノシロ",1],["ボラ",1]],"948":[["ホウボウ",1],["マダイ",1],["マハタ",1]],"950":[["スズキ",1]],"953":[["スズキ",2],["セイゴ（スズキ）",1]],"955":[["マハゼ",1]],"956":[["アジ",2]],"959":[["メバル",2],["タケノコメバル",1],["ドンコ",1]],"960":[["ゴンズイ",1]],"962":[["ドンコ",1],["フサギンポ",1]],"964":[["アジ",1],["セイゴ（スズキ）",1],["メッキ",1]],"966":[["ホウボウ",1],["マダイ",1]],"969":[["キビレ",1]],"974":[["アイナメ",3],["クロソイ",2],["ドンコ",1]],"975":[["アカカマス",1],["カマス",1]],"977":[["クロソイ",2],["メバル",1]],"979":[["アジ",5],["カマス",2],["アカカマス",1]],"982":[["アオリイカ",1]],"983":[["カサゴ",1]],"984":[["スズキ",2]],"987":[["アジ",1],["タケノコメバル",1],["メバル",1]],"992":[["キジハタ",1],["ミノカサゴ",1]],"996":[["カジカ",1],["クロソイ",1]],"998":[["アオリイカ",1]],"1004":[["タチウオ",2],["アジ",1],["スズキ",1]],"1006":[["カサゴ",1],["キジハタ",1],["スズキ",1]],"1008":[["マハゼ",2]],"1009":[["アジ",2],["クロメバル",2],["サバ",1]],"1011":[["アジ",1],["タケノコメバル",1]],"1012":[["カサゴ",3]],"1013":[["カサゴ",1],["セイゴ（スズキ）",1],["メバル",1]],"1023":[["スズキ",4]],"1024":[["カサゴ",2]],"1026":[["カマス",2],["セイゴ（ヒラスズキ）",2],["アジ",1]],"1032":[["クロメバル",1]],"1033":[["アジ",6],["タチウオ",4],["アオリイカ",1]],"1034":[["ヤリイカ",2],["イカ",1],["イワシ",1]],"1035":[["イセエビ",1]],"1036":[["スズキ",3],["カマス",2],["アジ",1]],"1039":[["カサゴ",2],["タケノコメバル",1],["メバル",1]],"1042":[["アオリイカ",3],["ハマフエフキ",2],["ゴマフエダイ",1]],"1043":[["アオリイカ",8],["イスズミ",1],["クロメジナ",1]],"1045":[["クロアナゴ",1]],"1046":[["タカノハダイ",1],["タコ",1]],"1049":[["アオリイカ",2],["アジ",1],["コウイカ",1]],"1050":[["アジ",1]],"1051":[["マハゼ",1]],"1053":[["マハゼ",7],["スズキ",2],["カレイ",1]],"1054":[["スズキ",1]],"1056":[["シマソイ",2]],"1057":[["アジ",1],["カサゴ",1],["タチウオ",1]],"1059":[["アジ",1],["クロメバル",1],["マアジ",1]],"1061":[["アジ",3],["マアジ",1]],"1063":[["アジ",19],["マアジ",11],["カサゴ",9]],"1064":[["アオリイカ",9],["アジ",9],["キジハタ",2]],"1066":[["アジ",3]],"1067":[["タチウオ",30]],"1068":[["アジ",1]],"1069":[["キジハタ",1]],"1071":[["アオリイカ",1],["アジ",1]],"1074":[["カサゴ",3],["アナゴ",1],["スズキ",1]],"1089":[["スズキ",2]],"1092":[["カサゴ",1]],"1093":[["アイナメ",1],["アジ",1],["クロソイ",1]],"1096":[["クロダイ",1],["シロメバル",1]],"1097":[["メバル",2]],"1098":[["タイ",1],["タナゴ",1]],"1103":[["スズキ",1]],"1104":[["ニゴイ",1]],"1109":[["カサゴ",1],["スズキ",1]],"1110":[["アオリイカ",4],["アジ",3],["ケンサキイカ",2]],"1112":[["クロソイ",1],["ドンコ",1],["メバル",1]],"1115":[["メバル",1]],"1116":[["タコ",1]],"1120":[["スズキ",3]],"1125":[["スズキ",2]],"1126":[["アオリイカ",5],["コウイカ",1],["コブシメ",1]],"1128":[["タケノコメバル",1],["メバル",1]],"1134":[["メバル",2],["アジ",1],["マダイ",1]],"1135":[["イットウダイ",1]],"1137":[["クロソイ",1]],"1143":[["アジ",1]],"1148":[["メバル",2]],"1152":[["カサゴ",1],["スズキ",1]],"1155":[["アオリイカ",2],["クロメバル",2],["アジ",1]],"1157":[["アオリイカ",4],["アジ",1],["タコ",1]],"1164":[["メバル",2],["アナゴ",1],["ドンコ",1]],"1165":[["アイナメ",1],["スズキ",1]],"1168":[["シロメバル",2]],"1172":[["タケノコメバル",1]],"1175":[["タチウオ",1],["ネンブツダイ",1]],"1179":[["スズキ",6],["クロダイ",1],["コイ",1]],"1180":[["アジ",3]],"1181":[["スズキ",8]],"1182":[["ヒイカ",8],["セイゴ（スズキ）",1]],"1185":[["アジ",1],["メバル",1]],"1187":[["アジ",3],["カサゴ",1],["キハダマグロ",1]],"1188":[["スズキ",1]],"1192":[["コモンフグ",2],["シロメバル",2],["カサゴ",1]],"1194":[["アジ",1],["カワハギ",1]],"1196":[["クロダイ",1]],"1199":[["メバル",4],["タケノコメバル",3],["クロソイ",2]],"1203":[["ケンサキイカ",1]],"1207":[["ニジマス",1]],"1209":[["ライギョ",1]],"1211":[["カサゴ",2],["アジ",1],["ハオコゼ",1]],"1212":[["タケノコメバル",1]],"1214":[["タチウオ",1],["マアジ",1]],"1225":[["メバル",8],["エゾメバル",2],["タケノコメバル",2]],"1231":[["メバル",1]],"1233":[["アイナメ",1],["マメイカ",1]],"1236":[["ワラサ",1]],"1237":[["スズキ",2]],"1241":[["ブラックバス",9],["ラージマウスバス",1]],"1243":[["アジ",2],["カサゴ",1]],"1244":[["スズキ",2]],"1250":[["ヤリイカ",2]],"1255":[["カサゴ",2]],"1258":[["アジ",1]],"1262":[["マアジ",1]],"1267":[["カサゴ",1]],"1270":[["スズキ",1]],"1275":[["スズキ",4],["アオリイカ",2],["マアジ",2]],"1280":[["アオリイカ",1],["コウイカ",1],["マアジ",1]],"1286":[["サバ",1]],"1293":[["クロソイ",3],["ドンコ",2],["アナゴ",1]],"1306":[["カサゴ",1]],"1309":[["スズキ",2],["カサゴ",1],["クロメバル",1]],"1310":[["クロソイ",1],["マゾイ",1]],"1311":[["タケノコメバル",2],["カサゴ",1],["メバル",1]],"1321":[["メバル",3],["アジ",2],["マハゼ",2]],"1325":[["アジ",2],["キジハタ",1]],"1326":[["アジ",1],["カサゴ",1],["スズキ",1]],"1327":[["カサゴ",1]],"1332":[["タチウオ",1]],"1335":[["スズキ",1]],"1336":[["イカ",2],["マゾイ",1],["ヤリイカ",1]],"1339":[["アオリイカ",2]],"1341":[["タイ",1]],"1351":[["スズキ",2]],"1355":[["アジ",1]],"1356":[["アジ",2]],"1359":[["アカカマス",1],["カサゴ",1]],"1361":[["クロソイ",1]],"1365":[["カサゴ",1]],"1368":[["カサゴ",2],["キジハタ",2]],"1372":[["マアジ",1],["ムツ",1],["ワラサ",1]],"1374":[["ミナミクロダイ",1]],"1376":[["スズキ",1]],"1377":[["サバ",1]],"1382":[["アジ",1]],"1385":[["アイナメ",4],["メバル",3],["シロメバル",2]],"1386":[["スズキ",3]],"1387":[["アオリイカ",1]],"1394":[["メバル",2],["アジ",1],["カサゴ",1]],"1397":[["ブラックバス",2]],"1399":[["タチウオ",1]],"1400":[["ケンサキイカ",1],["サバ",1],["マアジ",1]],"1402":[["コノシロ",1],["シロメバル",1],["メバル",1]],"1403":[["アジ",1],["マハゼ",1]],"1411":[["スズキ",1]],"1412":[["カサゴ",1],["キビレ",1]],"1416":[["シロメバル",1],["セイゴ（ヒラスズキ）",1]],"1418":[["アジ",4],["マアジ",1]],"1421":[["アジ",1]],"1432":[["メバル",3],["ドンコ",2]],"1434":[["アジ",1]],"1441":[["スズキ",1]],"1443":[["アジ",1],["カサゴ",1]],"1445":[["アジ",4]],"1448":[["ヒラマサ",1]],"1449":[["クロダイ",1],["スズキ",1]],"1455":[["アジ",1],["カワハギ",1],["キジハタ",1]],"1458":[["ハモ",1]],"1459":[["アカカマス",1],["ワラサ",1]],"1461":[["アオリイカ",1]],"1462":[["メバル",1]],"1463":[["ヒラマサ",1]],"1464":[["アジ",1]],"1467":[["アジ",2]],"1473":[["クロメバル",1],["ヒラスズキ",1],["マアジ",1]],"1474":[["アイナメ",1]],"1475":[["ヒラスズキ",1]],"1476":[["アオリイカ",2],["セイゴ（ヒラスズキ）",1],["タチウオ",1]],"1480":[["カニ",1]],"1481":[["アオリイカ",2],["カサゴ",1],["フッコ（ヒラスズキ）",1]],"1483":[["スズキ",1]],"1487":[["アオリイカ",2],["アカメバル",1]],"1488":[["アジ",2]],"1493":[["アジ",1]],"1496":[["ヒイカ",1]],"1502":[["クロダイ",1]],"1509":[["タケノコメバル",1]],"1524":[["アマダイ",1]],"1534":[["イセエビ",1]],"1535":[["コウイカ",1],["タチウオ",1]],"1536":[["アジ",5]],"1543":[["アオリイカ",12],["アジ",3],["ケンサキイカ",1]],"1549":[["キジハタ",1]],"1557":[["アジ",1],["イカ",1]],"1559":[["タチウオ",1]],"1561":[["スズキ",2],["アジ",1]],"1565":[["カサゴ",1]],"1573":[["コイ",2]],"1576":[["アジ",4],["カサゴ",2],["メバル",1]],"1580":[["クロダイ",2],["アジ",1],["カサゴ",1]],"1590":[["クロソイ",1]],"1593":[["アジ",1],["カサゴ",1]],"1603":[["アジ",1],["イトヨリダイ",1],["キス",1]],"1610":[["メバル",1]],"1614":[["メバル",1]],"1615":[["アジ",7],["カサゴ",2],["サバ",2]],"1624":[["タコ",2],["マダコ",2]],"1626":[["ネリゴ",1]],"1627":[["クエ",1]],"1633":[["アオリイカ",1],["ウグイ",1],["スズキ",1]],"1641":[["アジ",2]],"1646":[["アジ",3],["キビレ",1],["クロダイ",1]],"1666":[["ヤリイカ",1]],"1667":[["アジ",2],["イカ",1],["ギンガメアジ",1]],"1669":[["カマス",3],["アジ",1],["カサゴ",1]],"1673":[["カサゴ",1],["キジハタ",1],["スズキ",1]],"1674":[["カサゴ",2]],"1675":[["スズキ",2]],"1688":[["アジ",13],["セイゴ（スズキ）",4],["スズキ",1]],"1703":[["ブラックバス",1]],"1704":[["クロムツ",1],["ダイナンウミヘビ",1]],"1707":[["アジ",1],["スルメイカ",1],["ソイ",1]],"1714":[["アオリイカ",1]],"1717":[["スズキ",4],["キビレ",1]],"1730":[["スズキ",4],["ナイルティラピア",1]],"1735":[["ヒラスズキ",1]],"1743":[["アオリイカ",1],["キジハタ",1],["スズキ",1]],"1766":[["アジ",1],["カサゴ",1]],"1768":[["ソゲ",2],["エイ",1],["ダイナンウミヘビ",1]],"1772":[["クロダイ",1]],"1777":[["カサゴ",1],["メバル",1]],"1782":[["スズキ",11],["カサゴ",9],["アジ",7]],"1790":[["タケノコメバル",1]],"1791":[["アジ",1]],"1793":[["カサゴ",1]],"1798":[["アジ",1],["アナゴ",1],["ウッカリカサゴ",1]],"1800":[["カサゴ",1]],"1806":[["カサゴ",2]],"1813":[["アカメバル",1],["タコ",1],["ドンコ",1]],"1821":[["カサゴ",3]],"1822":[["カサゴ",2],["マアジ",2],["アジ",1]],"1823":[["アジ",4],["カサゴ",2],["サバ",1]],"1830":[["アカハタ",1],["キジハタ",1],["キビレ",1]],"1831":[["アオリイカ",1]],"1834":[["クロソイ",1]],"1837":[["メジナ",1]],"1841":[["メジナ",1]],"1844":[["クロムツ",1],["スズキ",1]],"1866":[["アジ",1]],"1867":[["クロムツ",1]],"1869":[["コマイ",1],["ニシン",1],["マハゼ",1]],"1873":[["アオリイカ",1],["ミナミハタンポ",1]],"1889":[["ケンサキイカ",1]],"1899":[["スズキ",3],["セイゴ（スズキ）",1],["ニゴイ",1]],"1902":[["カサゴ",1],["ガンド",1]],"1907":[["タケノコメバル",1]],"1913":[["アジ",2],["アナゴ",1],["シロメバル",1]],"1915":[["アイナメ",1],["クロソイ",1]],"1928":[["スズキ",1],["ブラックバス",1]],"1934":[["スズキ",1]],"1944":[["カサゴ",1],["キジハタ",1]],"1945":[["メジナ",1]],"1948":[["アオリイカ",2]],"1955":[["ブラックバス",1]],"1958":[["アジ",7],["メバル",2],["カサゴ",1]],"1967":[["アオリイカ",1]],"1968":[["メジナ",1]],"1970":[["マアナゴ",1]],"1976":[["スズキ",1]],"1977":[["スズキ",1]],"1981":[["セイゴ（スズキ）",1]],"2010":[["アオリイカ",1],["メアジ",1]],"2017":[["アジ",1],["クロダイ",1]],"2027":[["タケノコメバル",1],["マダコ",1]],"2028":[["コウイカ",1]],"2036":[["ヒイカ",1]],"2044":[["アジ",1]],"2051":[["スズキ",1]],"2057":[["アジ",1]],"2063":[["アジ",1]],"2070":[["スズキ",1]],"2088":[["スズキ",1]],"2110":[["メジナ",1]],"2111":[["アジ",4],["マアジ",1]],"2121":[["ケンサキイカ",2],["アオリイカ",1],["タコ",1]],"2130":[["メバル",1]],"2148":[["アナゴ",1],["カサゴ",1]],"2156":[["メバル",4],["ヒラメ",1]],"2159":[["カサゴ",3],["メバル",1]],"2162":[["ヒラメ",1]],"2167":[["スズキ",1]],"2168":[["ラージマウスバス",1]],"2171":[["クロメバル",1]],"2172":[["ワカサギ",1]],"2179":[["スズキ",1]],"2187":[["アオリイカ",1]],"2206":[["スズキ",2]],"2208":[["タケノコメバル",4],["アジ",2],["メバル",1]],"2216":[["スズキ",1],["メバル",1]],"2225":[["アジ",1]],"2246":[["アイナメ",1]],"2269":[["カサゴ",3],["アジ",2]],"2281":[["メジナ",1]],"2296":[["カサゴ",2],["アジ",1],["シロメバル",1]],"2297":[["アジ",1],["タケノコメバル",1]],"2309":[["アジ",1]],"2310":[["キジハタ",1]],"2319":[["セイゴ（スズキ）",1],["タケノコメバル",1]],"2364":[["スズキ",1]],"2376":[["カサゴ",1],["マアジ",1]],"2382":[["アジ",3],["カサゴ",1]],"2399":[["クロメバル",1]],"2418":[["ヤリイカ",1]],"2419":[["タケノコメバル",1]],"2433":[["カサゴ",1]],"2440":[["アイナメ",1],["アナゴ",1],["クロソイ",1]],"2444":[["スズキ",1]],"2501":[["クロソイ",2]],"2516":[["カサゴ",1]],"2533":[["ホタテウミヘビ",1]],"2572":[["スズキ",6]],"2573":[["アジ",1]],"2599":[["スズキ",1]],"2607":[["ブルックトラウト",1]],"2649":[["タチウオ",1]],"2667":[["クロメバル",1],["タチウオ",1]],"2675":[["アジ",2]],"2681":[["アジ",1],["マアジ",1]],"2683":[["カサゴ",1]],"2685":[["カサゴ",1],["ゴンズイ",1],["マタナゴ",1]],"2687":[["アジ",1]],"2692":[["コイ",1]],"2715":[["アジ",1]],"2760":[["サワラ",1],["ハモ",1],["マダイ",1]],"2770":[["メバル",2],["ガガネ",1],["スズキ",1]],"2794":[["セイゴ（ヒラスズキ）",1],["ヒラメ",1]],"2884":[["ヒラメ",1]],"3008":[["アジ",2],["シロメバル",2]],"3149":[["アジ",1],["メジナ",1],["メバル",1]],"3217":[["ヒラアジ",1]],"3347":[["アジ",1]],"3420":[["アオリイカ",1]],"3494":[["アジ",1]],"3978":[["アジ",6],["カサゴ",1],["クロダイ",1]],"3982":[["タチウオ",3],["カサゴ",1],["ゴンズイ",1]],"3985":[["サバ",1]],"4000":[["タチウオ",2],["カサゴ",1],["カマス",1]],"4003":[["キジハタ",2],["アジ",1],["トラフグ",1]],"4004":[["タチウオ",1]],"4005":[["アジ",1],["アナゴ",1],["イシモチ",1]],"4006":[["セイゴ（スズキ）",1]],"4013":[["ソイ",1],["マゾイ",1]],"4014":[["カサゴ",4],["アカメバル",1],["クジメ",1]],"4015":[["カサゴ",3]],"4016":[["アジ",4],["カサゴ",4],["タチウオ",3]],"4025":[["スズキ",1]],"4032":[["シロメバル",1],["メバル",1]],"4038":[["アジ",4]],"4046":[["アジ",3],["アオリイカ",1],["カサゴ",1]],"4094":[["スズキ",1]]}